Workbook

Sheet HDFC
A1: 88Academics
A2: Draft Pay Register for the month of September 2025
A4: PAY_DATE | B4: Employee Code | C4: Employee Name | D4: Date of Join | E4: Gender | F4: Date of Birth | G4: Date of Leaving | H4: Father Name | I4: Department | J4: Designation | K4: Cost_Centre | L4: Work Location | M4: UAN_No | N4: PAN | O4: Aadhaar Number | P4: Bank Name | Q4: Account_No | R4: IFSC_Code | S4: Name As Per Bank | T4: Nationality | U4: Mobile Number | V4: Email ID | W4: STDDAYS | X4: LOP DAYS | Y4: WRKDAYS | Z4: Basic | AA4: Basic Arrear | AB4: House Rent Allowance | AC4: HRA Arrear | AD4: Special Allowance | AE4: LOP Reversals | AF4: Total Salary | AG4: Salary Payable | AH4: TDS | AI4: Monthly TDS | AJ4: Provident Fund | AK4: PF Arrears | AL4: LWF | AM4: Net Salary Payable
AH5: 0
A6: 45930 | B6: 88A1004 | C6: Ajay Kumar Saxena | D6: 01/11/2021 | E6: M | F6: 20/06/1992 | H6: Late Jayant Kumar Lala | I6: Operations | J6: Manager | K6: NEW DELHI | L6: NEW DELHI | N6: DYDPS8248Q | O6: 336743542508 | P6: HDFC BANK LTD | Q6: 50100446028500 | R6: HDFC0004754 | S6: Ajay Kumar Saxena | T6: INDIAN | U6: 8527697925 | V6: aj.saxena0326@gmail.com | W6: 30 | X6: 0.6 | Y6: =W6-X6 -> 29.4 | Z6: 33275 | AA6: 0 | AB6: 16638 | AC6: 0 | AD6: 16638 | AF6: =SUM(Z6:AD6) -> 66551 | AG6: =ROUND(AF6/W6*Y6,0) -> 65220 | AJ6: 0 | AK6: 0 | AL6: 0 | AM6: =AG6-SUM(AI6:AL6) -> 65220 | AN6: 66551
A7: 45930 | B7: 88G1004 | C7: Simran Kumari Arora | D7: 01/11/2021 | E7: F | F7: 19/12/1996 | G7: 45930 | H7: Ramesh Arora | I7: Academic | J7: Asst. Manager | K7: NEW DELHI | L7: NEW DELHI | N7: DCXPA5508M | O7: 400878015992 | P7: HDFC BANK LTD | Q7: 50100367679688 | R7: HDFC0004754 | S7: Simran Arora | T7: INDIAN | U7: 7838783381 | V7: simranarora121996@gmail.com | W7: 30 | X7: 0 | Y7: =W7-X7 -> 30 | Z7: 0 | AA7: 0 | AB7: 0 | AC7: 0 | AD7: 0 | AF7: =SUM(Z7:AD7) -> 0 | AG7: =ROUND(AF7/W7*Y7,0) -> 0 | AJ7: 0 | AK7: 0 | AL7: 0 | AM7: =AG7-SUM(AI7:AL7) -> 0 | AP7: 23650
A8: 45930 | B8: 88G1013 | C8: Jyoti Pal | D8: 01/11/2021 | E8: F | F8: 22/05/1993 | H8: J.L Pal | I8: Marketing & Support | J8: Business Development Manager | K8: NEW DELHI | L8: NEW DELHI | N8: BRRPP8283K | O8: 863713103811 | P8: HDFC BANK LTD | Q8: 50100151532802 | R8: HDFC0000294 | S8: Jyoti Pal | T8: INDIAN | U8: 7982950540 | V8: sen.jyoti5@gmail.com | W8: 30 | X8: 0 | Y8: =W8-X8 -> 30 | Z8: 22000 | AA8: 0 | AB8: 11000 | AC8: 0 | AD8: 11000 | AF8: =SUM(Z8:AD8) -> 44000 | AG8: =ROUND(AF8/W8*Y8,0) -> 44000 | AJ8: 0 | AK8: 0 | AL8: 0 | AM8: =AG8-SUM(AI8:AL8) -> 44000 | AN8: 39600 | AO8: Increment
A9: 45930 | B9: 88G1032 | C9: Kiran Pathak | D9: 06/04/2022 | E9: F | F9: 09/07/1996 | G9: 45930 | H9: Mr. Shiv Charan Pathak | I9: Academic | J9: Asst. Manager | K9: NEW DELHI | L9: NEW DELHI | N9: DHPPP5580M | O9: 441344227722 | P9: HDFC BANK LTD | Q9: 50100570445568 | R9: HDFC0004754 | S9: Kiran Pathak | T9: INDIAN | U9: 9911369360 | V9: pathakkiran233@gmail.com | W9: 30 | X9: 0 | Y9: =W9-X9 -> 30 | Z9: 0 | AA9: 0 | AB9: 0 | AC9: 0 | AD9: 0 | AF9: =SUM(Z9:AD9) -> 0 | AG9: =ROUND(AF9/W9*Y9,0) -> 0 | AJ9: 0 | AK9: 0 | AL9: 0 | AM9: =AG9-SUM(AI9:AL9) -> 0 | AP9: 23650
A10: 45930 | B10: 88G1074 | C10: Rakesh Singh Rawat | D10: 14/03/2023 | E10: M | F10: 03/05/1976 | H10: Balwant Singh Rawat | I10: Academic | J10: Asst. Manager | K10: NEW DELHI | L10: NEW DELHI | N10: BUYPR5567C | O10: 621229408319 | P10: HDFC BANK LTD | Q10: 50100605279393 | R10: HDFC0003687 | S10: Rakesh Singh Rawat | T10: INDIAN | U10: 9013600858 | V10: rsrawatdtp9@gmail.com | W10: 30 | X10: 0 | Y10: =W10-X10 -> 30 | Z10: 21000 | AA10: 0 | AB10: 3200 | AC10: 0 | AD10: 0 | AF10: =SUM(Z10:AD10) -> 24200 | AG10: =ROUND(AF10/W10*Y10,0) -> 24200 | AJ10: 0 | AK10: 0 | AL10: 0 | AM10: =AG10-SUM(AI10:AL10) -> 24200 | AN10: 24200
A11: 45930 | B11: 88G1078 | C11: Pinku Kumar | D11: 10/05/2023 | E11: M | F11: 15/08/1996 | H11: Amresh Kumar Mishra | I11: VGLD | J11: SEO Executive | K11: NEW DELHI | L11: NEW DELHI | N11: CVZPK7257B | O11: 388227818863 | P11: HDFC BANK LTD | Q11: 50100754820324 | R11: HDFC0004754 | S11: Pinku Kumar | T11: INDIAN | U11: 9485963031 | V11: pinkudigitalmarketing@gmail.com | W11: 30 | X11: 0 | Y11: =W11-X11 -> 30 | Z11: 24100 | AA11: 0 | AB11: 12050 | AC11: 0 | AD11: 12050 | AF11: =SUM(Z11:AD11) -> 48200 | AG11: =ROUND(AF11/W11*Y11,0) -> 48200 | AJ11: 1800 | AK11: 0 | AL11: 0 | AM11: =AG11-SUM(AI11:AL11) -> 46400 | AN11: 46400
AH12: 0
B13: =COUNTA(B5:B11) -> 6 | G13: =COUNTA(G5:G11) -> 2 | T13: TOTAL | Z13: =SUM(Z5:Z12) -> 100375 | AA13: =SUM(AA5:AA12) -> 0 | AB13: =SUM(AB5:AB12) -> 42888 | AC13: =SUM(AC5:AC12) -> 0 | AD13: =SUM(AD5:AD12) -> 39688 | AF13: =SUM(AF5:AF12) -> 182951 | AG13: =SUM(AG5:AG12) -> 181620 | AI13: =SUM(AI5:AI12) -> 0 | AJ13: =SUM(AJ5:AJ12) -> 1800 | AK13: =SUM(AK5:AK12) -> 0 | AL13: =SUM(AL5:AL12) -> 0 | AM13: =SUM(AM5:AM12) -> 179820
Z15: 21000 | AA15: 0 | AB15: 5000 | AC15: 0 | AD15: 0 | AF15: =SUM(Z15:AD15) -> 26000
Z16: 22400 | AB16: 7600 | AF16: =SUM(Z16:AD16) -> 30000
Z17: =Z15-Z16 -> -1400 | AB17: =AB15-AB16 -> -2600

Sheet Draft-Paysheet May 2026
A1: 88Academics
A2: Draft Pay Register for the month of May 2026
P3: =AL3 -> 2693023.4 | Q3: 874538 | R3: =P3-Q3 -> 1818485.4 | AE3: =SUM(AE5:AE57) -> 2814163 | AL3: =SUBTOTAL(9,AL5:AL58) -> 2693023.4
A4: PAY_DATE | B4: Employee Code | C4: Employee Name | D4: Date of Join | E4: Gender | F4: Date of Birth | G4: Date of Leaving | H4: Father Name | I4: Department | J4: Designation | K4: Cost_Centre | L4: Work Location | M4: UAN_No | N4: PAN | O4: Aadhaar Number | P4: Bank Name | Q4: Account_No | R4: IFSC_Code | S4: Name As Per Bank | T4: Nationality | U4: Mobile Number | V4: Email ID | W4: STDDAYS | X4: LOP DAYS | Y4: WRKDAYS | Z4: Basic | AA4: Basic Arrear | AB4: House Rent Allowance | AC4: HRA Arrear | AD4: Special Allowance | AE4: Total Salary | AF4: Salary Payable | AG4: Other Banefit | AH4: Monthly TDS | AI4: Provident Fund | AJ4: Salary Deduction | AK4: LWF | AL4: Net Salary Payable
A5: 31-05-2026 | B5: 88A1001 | C5: Narayan Kasat | D5: 01/11/2021 | E5: M | F5: 27/06/1975 | H5: Mr. H.L.Kasat | I5: Management | J5: C.O.O | K5: NEW DELHI | L5: NEW DELHI | N5: AGAPK2560P | O5: 678252973676 | P5: AXIS BANK | Q5: 921010013386877 | R5: UTIB0004626 | S5: Narayan Kasat | T5: INDIAN | U5: 9891054411 | V5: narayan@88tuition.com | W5: 31 | Y5: =W5-X5 -> 31 | Z5: 150000 | AA5: 0 | AB5: 75000 | AC5: 0 | AD5: 75000 | AE5: =SUM(Z5:AD5) -> 300000 | AF5: =ROUND(AE5/W5*Y5,0) -> 300000 | AH5: =TDS!D25 -> 56907.5 | AI5: 0 | AJ5: 0 | AK5: 0 | AL5: =AF5-SUM(AH5:AK5) -> 243092.5
A6: 31-05-2026 | B6: 88A1002 | C6: Babu Lal | D6: 01/11/2021 | E6: M | F6: 07/02/1987 | H6: Bhagwan Sahay | I6: IT | J6: Project Head | K6: NEW DELHI | L6: NEW DELHI | N6: ADAPL0527A | O6: 725320397392 | P6: AXIS BANK | Q6: 911010047193187 | R6: UTIB0001007 | S6: Babu Lal | T6: INDIAN | U6: 9873030060 | V6: babulal0060@gmail.com | W6: 31 | Y6: =W6-X6 -> 31 | Z6: 99621 | AA6: 0 | AB6: 49810 | AC6: 0 | AD6: 49810 | AE6: =SUM(Z6:AD6) -> 199241 | AF6: =ROUND(AE6/W6*Y6,0) -> 199241 | AH6: =TDS!E25+2 -> 21989.753 | AI6: 0 | AJ6: 0 | AK6: 0 | AL6: =AF6-SUM(AH6:AK6) -> 177251.25
A7: 31-05-2026 | B7: 88A1003 | C7: Gulshan | D7: 01/11/2021 | E7: M | F7: 01/05/1999 | H7: J.P. Sharma | I7: Operations | J7: Manager | K7: NEW DELHI | L7: NEW DELHI | N7: CERPG0826H | O7: 830140509131 | P7: KARUR VYSYA BANK | Q7: 4101155000110629 | R7: KVBL0004101 | S7: Gulshan | T7: INDIAN | U7: 9717013679 | V7: gulshan12207@gmail.com | W7: 31 | Y7: =W7-X7 -> 31 | Z7: 47442 | AA7: 0 | AB7: 23721 | AC7: 0 | AD7: 23721 | AE7: =SUM(Z7:AD7) -> 94884 | AF7: =ROUND(AE7/W7*Y7,0) -> 94884 | AI7: 0 | AJ7: 0 | AK7: 0 | AL7: =AF7-SUM(AH7:AK7) -> 94884
A8: 31-05-2026 | B8: 88A1004 | C8: Ajay Kumar Saxena | D8: 01/11/2021 | E8: M | F8: 20/06/1992 | H8: Late Jayant Kumar Lala | I8: Operations | J8: Manager | K8: NEW DELHI | L8: NEW DELHI | N8: DYDPS8248Q | O8: 336743542508 | P8: HDFC BANK LTD | Q8: 50100446028500 | R8: HDFC0004754 | S8: Ajay Kumar Saxena | T8: INDIAN | U8: 8527697925 | V8: aj.saxena0326@gmail.com | W8: 31 | Y8: =W8-X8 -> 31 | Z8: =33275+3327-2 -> 36600 | AA8: 0 | AB8: =16638+1663-1 -> 18300 | AC8: 0 | AD8: =16638+1663-1 -> 18300 | AE8: =SUM(Z8:AD8) -> 73200 | AF8: =ROUND(AE8/W8*Y8,0) -> 73200 | AI8: 0 | AJ8: 0 | AK8: 0 | AL8: =AF8-SUM(AH8:AK8) -> 73200 | AN8: =AL8-AE8 -> 0
A9: 31-05-2026 | B9: 88G1001 | C9: Rashi Gupta | D9: 01/11/2021 | E9: F | F9: 19/03/1991 | H9: A. N. Gupta | I9: Academic | J9: Manager | K9: NEW DELHI | L9: NEW DELHI | N9: BDCPG4329J | O9: 366855676793 | P9: STATE BANK OF INDIA | Q9: 65122570810 | R9: SBIN0050324 | S9: Rashi Gupta | T9: INDIAN | U9: 9654365202 | V9: rashig350@gmail.com | W9: 31 | Y9: =W9-X9 -> 31 | Z9: 25000 | AA9: 0 | AB9: 6200 | AC9: 0 | AD9: 6200 | AE9: =SUM(Z9:AD9) -> 37400 | AF9: =ROUND(AE9/W9*Y9,0) -> 37400 | AI9: 0 | AJ9: 0 | AK9: 0 | AL9: =AF9-SUM(AH9:AK9) -> 37400
A10: 31-05-2026 | B10: 88G1003 | C10: Raj Kamal Sharma | D10: 01/11/2021 | E10: M | F10: 10/02/1989 | H10: Om Vir Sharma | I10: Academic | J10: Asst. Manager | K10: NEW DELHI | L10: NEW DELHI | N10: DEOPS7788G | O10: 432153723120 | P10: STATE BANK OF INDIA | Q10: 31582334723 | R10: SBIN0018166 | S10: Raj Kamal Sharma | T10: INDIAN | U10: 9968722755 | V10: 007kamalrajsharma@gmail.com | W10: 31 | Y10: =W10-X10 -> 31 | Z10: =21000+1000 -> 22000 | AA10: 0 | AB10: 7650 | AD10: 6650 | AE10: =SUM(Z10:AD10) -> 36300 | AF10: =ROUND(AE10/W10*Y10,0) -> 36300 | AG10: 1210 | AI10: 0 | AJ10: 0 | AK10: 0 | AL10: =AF10-SUM(AH10:AK10)+AG10 -> 37510
A11: 31-05-2026 | B11: 88G1007 | C11: Roshan Sharma | D11: 01/11/2021 | E11: M | F11: 14/06/1997 | H11: Jai Prakash Sharma | I11: Academic | J11: Asst. Manager | K11: NEW DELHI | L11: NEW DELHI | N11: CNJPR5123H | O11: 938129698636 | P11: BANK OF MAHARASHTRA | Q11: 60285501118 | R11: MAHB0001744 | S11: Roshan Sharma | T11: INDIAN | U11: 9911811713 | V11: roshansharma110043@gmail.com | W11: 31 | Y11: =W11-X11 -> 31 | Z11: 22138 | AA11: 0 | AB11: 11069 | AC11: 0 | AD11: 11069 | AE11: =SUM(Z11:AD11) -> 44276 | AF11: =ROUND(AE11/W11*Y11,0) -> 44276 | AI11: 0 | AJ11: 0 | AK11: 0 | AL11: =AF11-SUM(AH11:AK11) -> 44276
A12: 31-05-2026 | B12: 88G1011 | C12: Meenakshi Gosai | D12: 01/11/2021 | E12: F | F12: 05/01/1993 | H12: Late Kundan Lal | I12: Marketing & Support | J12: Business Development Manager | K12: NEW DELHI | L12: NEW DELHI | N12: BUQPG9684K | O12: 354855342339 | P12: INDIAN OVERSEAS BANK | Q12: 076601000061190 | R12: IOBA0000766 | S12: Meenakshi Gosai | T12: INDIAN | U12: 7042668809 | V12: meenakshigosai15@gmail.com | W12: 31 | Y12: =W12-X12 -> 31 | Z12: 23500 | AA12: 0 | AB12: =10750-500 -> 10250 | AC12: 0 | AD12: =10750-1500 -> 9250 | AE12: =SUM(Z12:AD12) -> 43000 | AF12: =ROUND(AE12/W12*Y12,0) -> 43000 | AI12: 0 | AJ12: 0 | AK12: 0 | AL12: =AF12-SUM(AH12:AK12) -> 43000
A13: 31-05-2026 | B13: 88G1012 | C13: Deepa Chandnani | D13: 01/11/2021 | E13: F | F13: 10/02/1989 | H13: Ghanshyam Bharwani | I13: Marketing & Support | J13: Business Development Manager | K13: NEW DELHI | L13: NEW DELHI | N13: AVLPB5695G | O13: 563133225753 | P13: STATE BANK OF INDIA | Q13: 51116630705 | R13: SBIN0032160 | S13: Deepa Chandnani | T13: INDIAN | U13: 9873452523 | V13: deepabharwanis@gmail.com | W13: 31 | Y13: =W13-X13 -> 31 | Z13: 23500 | AA13: 0 | AB13: 10500 | AC13: 0 | AD13: =9500-1500 -> 8000 | AE13: =SUM(Z13:AD13) -> 42000 | AF13: =ROUND(AE13/W13*Y13,0) -> 42000 | AI13: 0 | AJ13: 0 | AK13: 0 | AL13: =AF13-SUM(AH13:AK13) -> 42000
A14: 31-05-2026 | B14: 88G1013 | C14: Jyoti Pal | D14: 01/11/2021 | E14: F | F14: 22/05/1993 | H14: J.L Pal | I14: Marketing & Support | J14: Business Development Manager | K14: NEW DELHI | L14: NEW DELHI | N14: BRRPP8283K | O14: 863713103811 | P14: HDFC BANK LTD | Q14: 50100151532802 | R14: HDFC0000294 | S14: Jyoti Pal | T14: INDIAN | U14: 7982950540 | V14: sen.jyoti5@gmail.com | W14: 31 | Y14: =W14-X14 -> 31 | Z14: 24000 | AA14: 0 | AB14: 11000 | AC14: 0 | AD14: 9000 | AE14: =SUM(Z14:AD14) -> 44000 | AF14: =ROUND(AE14/W14*Y14,0) -> 44000 | AI14: 0 | AJ14: 0 | AK14: 0 | AL14: =AF14-SUM(AH14:AK14) -> 44000
A15: 31-05-2026 | B15: 88G1014 | C15: Nidhi Gupta | D15: 01/11/2021 | E15: F | F15: 27/10/1975 | H15: J. P. Gupta | I15: Marketing & Support | J15: Business Development Manager | K15: NEW DELHI | L15: NEW DELHI | N15: AEEPG1703Q | O15: 840497171317 | P15: Canara Bank | Q15: 110037818923 | R15: CNRB0003160 | S15: Nidhi Gupta | T15: INDIAN | U15: 9958127672 | V15: nidhi.gupta.ng90@gmail.com | W15: 31 | X15: =LOP!R21 -> 1.5 | Y15: =W15-X15 -> 29.5 | Z15: =24000+2400 -> 26400 | AA15: 0 | AB15: =8292+829 -> 9121 | AD15: =5292+529 -> 5821 | AE15: =SUM(Z15:AD15) -> 41342 | AF15: =ROUND(AE15/W15*Y15,0) -> 39342 | AI15: 0 | AJ15: 0 | AK15: 0 | AL15: =AF15-SUM(AH15:AK15) -> 39342
A16: 31-05-2026 | B16: 88G1022 | C16: Shalini Sharma | D16: 03/02/2022 | E16: F | F16: 03/07/1990 | H16: BINNI SHARMA | I16: Academic | J16: Manager | K16: NEW DELHI | L16: NEW DELHI | N16: DFDPS2978C | O16: 390094950274 | P16: STATE BANK OF INDIA | Q16: 20088263301 | R16: SBIN0011550 | S16: Shalini Sharma | T16: Indian | U16: 9999868854 | V16: sharmashalini0307@gmail.com | W16: 31 | Y16: =W16-X16 -> 31 | Z16: 22000 | AA16: 0 | AB16: 4500 | AC16: 0 | AD16: 3500 | AE16: =SUM(Z16:AD16) -> 30000 | AF16: =ROUND(AE16/W16*Y16,0) -> 30000 | AI16: 0 | AJ16: 0 | AK16: 0 | AL16: =AF16-SUM(AH16:AK16) -> 30000
A17: 31-05-2026 | B17: 88G1041 | C17: Vikas Panwar | D17: 01/07/2022 | E17: M | F17: 15/08/1994 | H17: Dilip Keshri | I17: IT | J17: Asst. Manager | K17: NEW DELHI | L17: NEW DELHI | N17: DNMPP4480B | O17: 557891030486 | P17: KOTAK MAHINDRA BANK | Q17: 5246430031 | R17: KKBK0004596 | S17: Vikas Panwar | T17: INDIAN | U17: 8755629335 | V17: vikashpanwar888@gmail.com | W17: 31 | Y17: =W17-X17 -> 31 | Z17: =24000+2400 -> 26400 | AA17: 0 | AB17: =7600-3000+460+40 -> 5100 | AC17: 0 | AD17: 0 | AE17: =SUM(Z17:AD17) -> 31500 | AF17: =ROUND(AE17/W17*Y17,0) -> 31500 | AI17: 0 | AJ17: 0 | AK17: 0 | AL17: =AF17-SUM(AH17:AK17) -> 31500
A18: 31-05-2026 | B18: 88G1064 | C18: Maheen Ajmali | D18: 13/10/2022 | E18: F | F18: 04/08/1997 | H18: Mohd Arif Ajmali | I18: Marketing & Support | J18: Business Development Manager | K18: NEW DELHI | L18: NEW DELHI | N18: CXGPA1055G | O18: 299829943417 | P18: STATE BANK OF INDIA | Q18: 35853508559 | R18: SBIN0005918 | S18: Maheen Ajmali | T18: INDIAN | U18: 9873907268 | V18: maheenajmali974@gmail.com | W18: 31 | Y18: =W18-X18 -> 31 | Z18: 23000 | AA18: 0 | AB18: 5600 | AC18: 0 | AD18: 0 | AE18: =SUM(Z18:AD18) -> 28600 | AF18: =ROUND(AE18/W18*Y18,0) -> 28600 | AI18: 0 | AJ18: 0 | AK18: 0 | AL18: =AF18-SUM(AH18:AK18) -> 28600
A19: 31-05-2026 | B19: 88G1078 | C19: Pinku Kumar | D19: 10/05/2023 | E19: M | F19: 15/08/1996 | H19: Amresh Kumar Mishra | I19: VGLD | J19: SEO Executive | K19: NEW DELHI | L19: NEW DELHI | N19: CVZPK7257B | O19: 388227818863 | P19: HDFC BANK LTD | Q19: 50100754820324 | R19: HDFC0004754 | S19: Pinku Kumar | T19: INDIAN | U19: 9485963031 | V19: pinkudigitalmarketing@gmail.com | W19: 31 | Y19: =W19-X19 -> 31 | Z19: 28100 | AA19: 0 | AB19: 12050 | AC19: 0 | AD19: 8050 | AE19: =SUM(Z19:AD19) -> 48200 | AF19: =ROUND(AE19/W19*Y19,0) -> 48200 | AG19: 0 | AI19: 1800 | AJ19: 0 | AK19: 0 | AL19: =AF19-SUM(AH19:AK19)-AG19 -> 46400
A20: 31-05-2026 | B20: 88G1087 | C20: Arpit Acharya | D20: 30/10/2023 | E20: M | F20: 23/09/1997 | H20: Vimal Acharya | I20: VGLD | J20: Business Development Manager | K20: NEW DELHI | L20: NEW DELHI | N20: CQVPA0022P | O20: 928630894864 | P20: HDFC BANK LTD | Q20: 50100823730034 | R20: HDFC0007285 | S20: Arpit Acharya | T20: INDIAN | U20: 8268890388 | V20: arpitacharya23@gmail.com | W20: 31 | Y20: =W20-X20 -> 31 | Z20: 27912 | AA20: 0 | AB20: 13957 | AC20: 0 | AD20: 13957 | AE20: =SUM(Z20:AD20) -> 55826 | AF20: =ROUND(AE20/W20*Y20,0) -> 55826 | AI20: 1800 | AJ20: 0 | AK20: 0 | AL20: =AF20-SUM(AH20:AK20) -> 54026
A21: 31-05-2026 | B21: 88V1003 | C21: Rachna Ajmani | D21: 01/11/2021 | E21: F | F21: 02/10/1980 | H21: Lt. Sh. Harish Chander Batra | I21: VGLD | J21: Business Development Manager | K21: NEW DELHI | L21: NEW DELHI | N21: BHIPA7769N | O21: 215770644706 | P21: HDFC BANK LTD | Q21: 50100067622091 | R21: HDFC0001657 | S21: Rachna Ajmani | T21: INDIAN | U21: 8527697922 | V21: rachna@vglearningdestination.com | W21: 31 | X21: =LOP!R27 -> 1 | Y21: =W21-X21 -> 30 | Z21: =24000+2400 -> 26400 | AA21: 0 | AB21: =6000+600 -> 6600 | AC21: 0 | AD21: =3000+300 -> 3300 | AE21: =SUM(Z21:AD21) -> 36300 | AF21: =ROUND(AE21/W21*Y21,0) -> 35129 | AI21: 0 | AJ21: 0 | AK21: 0 | AL21: =AF21-SUM(AH21:AK21) -> 35129
A22: 31-05-2026 | B22: 88V1012 | C22: Sandeep Maurya | D22: 02/01/2022 | E22: M | F22: 25/08/1997 | H22: Jayprakash Maurya | I22: IT | J22: Mobile Application Developer | K22: NEW DELHI | L22: NEW DELHI | N22: DEFPM3399Q | O22: 233161412775 | P22: ICICI Bank | Q22: 051601003530 | R22: ICIC0000815 | S22: Sandeep Maurya | T22: INDIAN | U22: 7379258598 | V22: me.sandy00@gmail.com | W22: 31 | Y22: =W22-X22 -> 31 | Z22: 41182 | AA22: 0 | AB22: 20591 | AC22: 0 | AD22: 20591 | AE22: =SUM(Z22:AD22) -> 82364 | AF22: =ROUND(AE22/W22*Y22,0) -> 82364 | AI22: 0 | AJ22: 0 | AK22: 0 | AL22: =AF22-SUM(AH22:AK22) -> 82364
A23: 31-05-2026 | B23: 88V1018 | C23: Priya Madan | D23: 01/08/2022 | E23: F | F23: 03/03/1985 | H23: SUBHASH BANGERA | I23: VGLD | J23: Business Development Manager | K23: NEW DELHI | L23: NEW DELHI | N23: APQPB6598D | O23: 941384090856 | P23: AXIS BANK | Q23: 911010066143864 | R23: UTIB0000739 | S23: Priya Madan | T23: INDIAN | U23: 9654797629 | V23: priya.madan331985@gmail.com | W23: 31 | X23: 2 | Y23: =W23-X23 -> 29 | Z23: =22026+2203 -> 24229 | AA23: 0 | AB23: =7637+764 -> 8401 | AD23: =6637+663 -> 7300 | AE23: =SUM(Z23:AD23) -> 39930 | AF23: =ROUND(AE23/W23*Y23,0) -> 37354 | AH23: 0 | AI23: 0 | AJ23: 515 | AK23: 0 | AL23: =AF23-SUM(AH23:AK23)+AG23 -> 36839
A24: 31-05-2026 | B24: 88V1024 | C24: Monika Dhingra | D24: 19/12/2022 | E24: F | F24: 11/11/1982 | I24: VGLD | J24: Evaluation Support Executive | K24: NEW DELHI | L24: NEW DELHI | N24: AGKPD1159K | O24: 936304152231 | P24: ICICI Bank | Q24: 630101511988 | R24: ICIC0006301 | S24: Monika Dhingra | T24: INDIAN | U24: 9873040788 | V24: monikadh11@gmail.com | W24: 31 | Y24: =W24-X24 -> 31 | Z24: 23100 | AA24: 0 | AB24: 8250 | AC24: 0 | AD24: 8250 | AE24: =SUM(Z24:AD24) -> 39600 | AF24: =ROUND(AE24/W24*Y24,0) -> 39600 | AI24: 0 | AJ24: 0 | AK24: 0 | AL24: =AF24-SUM(AH24:AK24) -> 39600
A25: 31-05-2026 | B25: 88V1029 | C25: Sandeep | D25: 01/04/2023 | E25: M | F25: 28/11/1987 | H25: Shri Sudama Prasad Gupta | I25: VGLD | J25: Operations Executive | K25: NEW DELHI | L25: NEW DELHI | N25: BTAPS8845P | O25: 683236866217 | P25: HDFC BANK LTD | Q25: 50100255004836 | R25: HDFC0000026 | S25: Sandeep | T25: INDIAN | U25: 9582781076 | V25: sandeepguptaseo@gmail.com | W25: 31 | Y25: =W25-X25 -> 31 | Z25: 23100 | AA25: 0 | AB25: 7480 | AC25: 0 | AD25: 0 | AE25: =SUM(Z25:AD25) -> 30580 | AF25: =ROUND(AE25/W25*Y25,0) -> 30580 | AI25: 0 | AJ25: 0 | AK25: 0 | AL25: =AF25-SUM(AH25:AK25) -> 30580
A26: 31-05-2026 | B26: 88V1032 | C26: Mohd Ubaid | D26: 01/04/2023 | E26: M | F26: 15/06/1997 | H26: Mohd Haseen | I26: VGLD | J26: Business Development Manager | K26: NEW DELHI | L26: NEW DELHI | N26: AHEPU6987F | O26: 950525699650 | P26: HDFC BANK LTD | Q26: 50100262389811 | R26: HDFC0000708 | S26: Mohd Ubaid | T26: INDIAN | U26: 9999314704 | V26: ubaidkhan6166@gmail.com | W26: 31 | Y26: =W26-X26 -> 31 | Z26: 38800 | AA26: 0 | AB26: 18900 | AC26: 0 | AD26: 18900 | AE26: =SUM(Z26:AD26) -> 76600 | AF26: =ROUND(AE26/W26*Y26,0) -> 76600 | AI26: 1800 | AJ26: 0 | AK26: 0 | AL26: =AF26-SUM(AH26:AK26) -> 74800
A27: 31-05-2026 | B27: 88V1033 | C27: Jyoti Singh | D27: 01/04/2023 | E27: F | F27: 05/10/1997 | H27: Late Mr Madan pal Singh | I27: VGLD | J27: Operations Executive | K27: NEW DELHI | L27: NEW DELHI | N27: LXKPS2332B | O27: 335290214255 | P27: ICICI Bank | Q27: 721801500772 | R27: ICIC0007218 | S27: Jyoti Singh | T27: INDIAN | U27: 7982537821 | V27: jyotisingh23839@gmail.com | W27: 31 | Y27: =W27-X27 -> 31 | Z27: 23100 | AA27: 0 | AB27: 7150 | AC27: 0 | AD27: 0 | AE27: =SUM(Z27:AD27) -> 30250 | AF27: =ROUND(AE27/W27*Y27,0) -> 30250 | AI27: 0 | AJ27: 0 | AK27: 0 | AL27: =AF27-SUM(AH27:AK27) -> 30250
A28: 31-05-2026 | B28: 88V1035 | C28: Sugandha Bhatnagar | D28: 01/04/2023 | E28: F | F28: 22/05/1988 | H28: Vivek bhatnagar | I28: VGLD | J28: Business Development Manager | K28: NEW DELHI | L28: NEW DELHI | N28: BJYPB9879A | O28: 756329670090 | P28: Indian Bank | Q28: 59084158508 | R28: IDIB000T553 | S28: Sugandha | T28: INDIAN | U28: 8534999427 | V28: sugandhabhatnagar0121@gmail.com | W28: 31 | Y28: =W28-X28 -> 31 | Z28: 23100 | AA28: 0 | AB28: 7700 | AC28: 0 | AD28: 7700 | AE28: =SUM(Z28:AD28) -> 38500 | AF28: =ROUND(AE28/W28*Y28,0) -> 38500 | AI28: 0 | AJ28: 0 | AK28: 0 | AL28: =AF28-SUM(AH28:AK28) -> 38500
A29: 31-05-2026 | B29: 88V1047 | C29: Porikhit Das | D29: 14/08/2023 | E29: M | F29: 10/10/1994 | H29: Raju Das | I29: VGLD | J29: Business Development Manager | K29: NEW DELHI | L29: NEW DELHI | N29: BXHPD3077M | O29: 361057786305 | P29: KOTAK MAHINDRA BANK | Q29: 7546347903 | R29: KKBK0004575 | S29: Porikhit Das | T29: INDIAN | U29: 8135820955 | V29: porikhitdas16@gmail.com | W29: 31 | X29: =LOP!R36 -> 2 | Y29: =W29-X29 -> 29 | Z29: 30250 | AA29: 0 | AB29: 15125 | AC29: 0 | AD29: 15125 | AE29: =SUM(Z29:AD29) -> 60500 | AF29: =ROUND(AE29/W29*Y29,0) -> 56597 | AI29: 0 | AJ29: 0 | AK29: 0 | AL29: =AF29-SUM(AH29:AK29)-AG29 -> 56597
A30: 31-05-2026 | B30: 88V1050 | C30: Manazir | D30: 18/09/2023 | E30: M | F30: 10/09/2000 | H30: Afaq Ahmad | I30: VGLD | J30: Business Development Manager | K30: NEW DELHI | L30: NEW DELHI | N30: EYZPM8286B | O30: 629843778596 | P30: HDFC BANK LTD | Q30: 50100683165229 | R30: HDFC0004754 | S30: Manazir | T30: INDIAN | U30: 7678985427 | V30: mr.afaq12345@gmail.com | W30: 31 | Y30: =W30-X30 -> 31 | Z30: 24750 | AA30: 0 | AB30: 12375 | AC30: 0 | AD30: 12375 | AE30: =SUM(Z30:AD30) -> 49500 | AF30: =ROUND(AE30/W30*Y30,0) -> 49500 | AI30: 0 | AJ30: 0 | AK30: 0 | AL30: =AF30-SUM(AH30:AK30) -> 49500 | AN30: =AE30-AL30 -> 0
A31: 31-05-2026 | B31: 88V1051 | C31: Shohrab Haidar | D31: 01/09/2023 | E31: M | F31: 20/04/1998 | H31: Afzal hussain | I31: VGLD | J31: Business Development Manager | K31: NEW DELHI | L31: NEW DELHI | N31: ARPPH2377D | O31: 634825133916 | P31: PUNJAB AND SIND BANK | Q31: 14952122003500 | R31: PUNB0509610 | S31: Shohrab Haidar | T31: INDIAN | U31: 9773605547 | V31: sohrabhaider97@gmail.com | W31: 31 | Y31: =W31-X31 -> 31 | Z31: 26500 | AA31: 0 | AB31: 9000 | AC31: 0 | AD31: 6500 | AE31: =SUM(Z31:AD31) -> 42000 | AF31: =ROUND(AE31/W31*Y31,0) -> 42000 | AI31: 0 | AJ31: 0 | AK31: 0 | AL31: =AF31-SUM(AH31:AK31) -> 42000
A32: 31-05-2026 | B32: 88V1052 | C32: Anita Dubey | D32: 16/11/2023 | E32: F | F32: 12/08/1976 | H32: P DP CHOURASIA | I32: VGLD | J32: General Manager | K32: NEW DELHI | L32: NEW DELHI | N32: AMFPD7530B | O32: 765803347470 | P32: ICICI Bank | Q32: 631201503816 | R32: ICIC0006312 | S32: Anita Dubey | T32: INDIAN | U32: 9912990661 | V32: anitadubay@gmail.com | W32: 31 | Y32: =W32-X32 -> 31 | Z32: 54167 | AA32: 0 | AB32: 27083 | AC32: 0 | AD32: 27083 | AE32: =SUM(Z32:AD32) -> 108333 | AF32: =ROUND(AE32/W32*Y32,0) -> 108333 | AH32: =TDS!F52 -> 6315.3935 | AI32: 0 | AJ32: 0 | AK32: 0 | AL32: =AF32-SUM(AH32:AK32) -> 102017.61
A33: 31-05-2026 | B33: 88V1062 | C33: Parth Dilip Saraiya | D33: 22/01/2024 | E33: M | F33: 14/04/1995 | H33: Dilip Prabhudas Saraiya | I33: VGLD | J33: Sr. Executive | K33: NEW DELHI | L33: NEW DELHI | N33: FUNPS2736H | O33: 384092122476 | P33: HDFC BANK LTD | Q33: 50100461863868 | R33: HDFC0000489 | S33: Parth Dilip Saraiya | T33: INDIAN | U33: 7506327714 | V33: parthsaraiya77@gmail.com | W33: 31 | Y33: =W33-X33 -> 31 | Z33: 43920 | AA33: 0 | AB33: 19440 | AC33: 0 | AD33: 14640 | AE33: =SUM(Z33:AD33) -> 78000 | AF33: =ROUND(AE33/W33*Y33,0) -> 78000 | AI33: 0 | AJ33: 0 | AK33: 0 | AL33: =AF33-SUM(AH33:AK33) -> 78000
A34: 31-05-2026 | B34: 88V1067 | C34: Sangita Chaurasia | D34: 08/02/2024 | E34: F | F34: 30/03/1974 | H34: Sangeeta Chourasia | I34: VGLD | J34: Senior Business Development Manager | K34: NEW DELHI | L34: NEW DELHI | N34: AGFPC0825Q | O34: 415140302515 | P34: HDFC BANK LTD | Q34: 12281050015374 | R34: HDFC0001228 | S34: Sangeeta Chourasia | T34: INDIAN | U34: 7893566120 | V34: sangeetachourasia1977@gmail.com | W34: 31 | Y34: =W34-X34 -> 31 | Z34: 35457 | AA34: 0 | AB34: 16032 | AC34: 0 | AD34: 12511 | AE34: =SUM(Z34:AD34) -> 64000 | AF34: =ROUND(AE34/W34*Y34,0) -> 64000 | AI34: 0 | AJ34: 0 | AK34: 0 | AL34: =AF34-SUM(AH34:AK34)+AG34 -> 64000
A35: 31-05-2026 | B35: 88V1076 | C35: Alok Kumar Srivastava | D35: 01/04/2024 | E35: M | F35: 02/01/1977 | H35: Awdesh prasad | I35: VGLD | J35: Manager | K35: NEW DELHI | L35: NEW DELHI | N35: BSCPS3651L | O35: 881174158755 | P35: HDFC BANK LTD | Q35: 50100197657364 | R35: HDFC0004754 | S35: Alok Kumar Srivastava | T35: Indian | U35: 9268048522 | V35: aloksrivastva01@gmail.com | W35: 31 | Y35: =W35-X35 -> 31 | Z35: =25000+2500 -> 27500 | AA35: 0 | AB35: =11000+1100 -> 12100 | AC35: 0 | AD35: =8000+800 -> 8800 | AE35: =SUM(Z35:AD35) -> 48400 | AF35: =ROUND(AE35/W35*Y35,0) -> 48400 | AI35: 0 | AJ35: 0 | AK35: 0 | AL35: =AF35-SUM(AH35:AK35) -> 48400
A36: 31-05-2026 | B36: 88V1077 | C36: Aman Kumar | D36: 08/04/2024 | E36: M | F36: 03/02/2001 | H36: Ashok Kumar | I36: VGLD | J36: Business Development Manager | K36: NEW DELHI | L36: NEW DELHI | N36: JUSPK9115H | O36: 940911811731 | P36: HDFC BANK LTD | Q36: 50100832643671 | R36: HDFC0004754 | S36: Aman Kumar | T36: Indian | U36: 7678231846 | V36: amanammu0001@gmail.com | W36: 31 | Y36: =W36-X36 -> 31 | Z36: 23500 | AA36: 0 | AB36: 5500 | AC36: 0 | AD36: 0 | AE36: =SUM(Z36:AD36) -> 29000 | AF36: =ROUND(AE36/W36*Y36,0) -> 29000 | AI36: 0 | AJ36: 0 | AK36: 0 | AL36: =AF36-SUM(AH36:AK36) -> 29000
A37: 31-05-2026 | B37: 88V1085 | C37: Manmohan Singh Rawat | D37: 17/05/2024 | E37: M | F37: 20/07/1982 | H37: L S Rawat | I37: VGLD | J37: General Manager | K37: NEW DELHI | L37: NEW DELHI | N37: AKKPR9916L | O37: 988868176956 | P37: HDFC BANK LTD | Q37: 50100286871518 | R37: HDFC0002005 | S37: Manmohan Singh Rawat | T37: Indian | U37: 9643817909 | V37: rawatsinghmanmohan@gmail.com | W37: 31 | Y37: =W37-X37 -> 31 | Z37: 37400 | AA37: 0 | AB37: 18700 | AC37: 0 | AD37: 18700 | AE37: =SUM(Z37:AD37) -> 74800 | AF37: =ROUND(AE37/W37*Y37,0) -> 74800 | AI37: 0 | AJ37: 0 | AK37: 0 | AL37: =AF37-SUM(AH37:AK37) -> 74800
A38: 31-05-2026 | B38: 88V1089 | C38: Chetan Bisht | D38: 10/06/2024 | E38: M | F38: 07/07/1999 | H38: Narottam Bisht | I38: VGLD | J38: Senior Business Development Manager | K38: NEW DELHI | L38: NEW DELHI | N38: CZSPB6257M | O38: 781244878416 | P38: AXIS BANK | Q38: 922010024097820 | R38: UTIB0004122 | S38: Chetan Bisht | T38: Indian | U38: 9315688493 | V38: chetanbisht2715@gmail.com | W38: 31 | Y38: =W38-X38 -> 31 | Z38: 27500 | AA38: 0 | AB38: 13750 | AC38: 0 | AD38: 13750 | AE38: =SUM(Z38:AD38) -> 55000 | AF38: =ROUND(AE38/W38*Y38,0) -> 55000 | AI38: 0 | AJ38: 0 | AK38: 0 | AL38: =AF38-SUM(AH38:AK38) -> 55000
A39: 31-05-2026 | B39: 88V1090 | C39: Nitin Parashar | D39: 10/06/2024 | E39: M | F39: 01/04/1998 | H39: Manoj Parashar | I39: VGLD | J39: Business Development Manager | K39: NEW DELHI | L39: NEW DELHI | N39: DCTPP9267A | O39: 200341906859 | P39: HDFC BANK LTD | Q39: 50100744847754 | R39: HDFC0000279 | S39: Nitin Parashar | T39: Indian | U39: 9582026264 | V39: nitinparashar43@gmail.com | W39: 31 | Y39: =W39-X39 -> 31 | Z39: 23100 | AA39: 0 | AB39: 11550 | AC39: 0 | AD39: 11550 | AE39: =SUM(Z39:AD39) -> 46200 | AF39: =ROUND(AE39/W39*Y39,0) -> 46200 | AI39: 0 | AJ39: 0 | AK39: 0 | AL39: =AF39-SUM(AH39:AK39) -> 46200
A40: 31-05-2026 | B40: 88V1091 | C40: Sanjay Tewari | D40: 10/06/2024 | E40: M | F40: 01/07/1990 | H40: Lalit Prasad Tewari | I40: VGLD | J40: Business Development Executive | K40: NEW DELHI | L40: NEW DELHI | N40: AJKPT5665R | O40: 429920718466 | P40: HDFC BANK LTD | Q40: 50100485721253 | R40: HDFC0002061 | S40: Sanjay Tewari | T40: Indian | U40: 9999476208 | V40: sanjay01tewari@gmail.com | W40: 31 | X40: =LOP!R50 -> 0.5 | Y40: =W40-X40 -> 30.5 | Z40: 22000 | AA40: 0 | AB40: =4000-1000 -> 3000 | AC40: 0 | AD40: 0 | AE40: =SUM(Z40:AD40) -> 25000 | AF40: =ROUND(AE40/W40*Y40,0) -> 24597 | AI40: 0 | AJ40: 0 | AK40: 0 | AL40: =AF40-SUM(AH40:AK40) -> 24597
A41: 31-05-2026 | B41: 88V1098 | C41: Unnati Sharma | D41: 01/08/2024 | E41: F | F41: 20/12/1999 | H41: Mukesh | I41: Marketing & Support | J41: Executive | K41: NEW DELHI | L41: NEW DELHI | N41: AKCPU5172F | O41: 462728519001 | P41: CENTRAL BANK OF INDIA | Q41: 3398624832 | R41: CBIN0280320 | S41: Unnati Sharma | T41: Indian | U41: 9870106997 | V41: unnatisharma62@gmail.com | W41: 31 | Y41: =W41-X41 -> 31 | Z41: 24640 | AA41: 0 | AB41: 8360 | AC41: 0 | AD41: 0 | AE41: =SUM(Z41:AD41) -> 33000 | AF41: =ROUND(AE41/W41*Y41,0) -> 33000 | AI41: 0 | AJ41: 0 | AK41: 0 | AL41: =AF41-SUM(AH41:AK41) -> 33000
A42: 31-05-2026 | B42: 88V1100 | C42: Hrithik Katyal | D42: 03/09/2024 | E42: M | F42: 20/12/1999 | H42: Kharaiti katyal | I42: VGLD | J42: Business Development Manager | K42: NEW DELHI | L42: NEW DELHI | N42: ILOPK3118L | O42: 291203908019 | P42: Canara Bank | Q42: 2751101037034 | R42: CNRB0002751 | S42: Hrithik Katyal | T42: Indian | U42: 7838179299 | V42: hrithikkatyal62@gmail.com | W42: 31 | Y42: =W42-X42 -> 31 | Z42: 26300 | AA42: 0 | AB42: 13150 | AC42: 0 | AD42: 13150 | AE42: =SUM(Z42:AD42) -> 52600 | AF42: =ROUND(AE42/W42*Y42,0) -> 52600 | AI42: 0 | AJ42: 0 | AK42: 0 | AL42: =AF42-SUM(AH42:AK42)+AG42 -> 52600
A43: 31-05-2026 | B43: 88V1105 | C43: Naved Emamuddin Chauhan | D43: 06/11/2024 | E43: M | F43: 15/03/1999 | H43: Emamuddin Chauhan | I43: VGLD | J43: Sr. Business Development Executive | K43: NEW DELHI | L43: NEW DELHI | N43: BWXPC1258G | O43: 768700882613 | P43: HDFC BANK LTD | Q43: 50100403118930 | R43: HDFC0000411 | S43: Naved Emamuddin Chauhan | T43: Indian | U43: 8898498128 | V43: navedmansuri210@gmail.com | W43: 31 | Y43: =W43-X43 -> 31 | Z43: 24773 | AA43: 0 | AB43: 12386 | AC43: 0 | AD43: 12386 | AE43: =SUM(Z43:AD43) -> 49545 | AF43: =ROUND(AE43/W43*Y43,0) -> 49545 | AI43: 0 | AJ43: 0 | AK43: 0 | AL43: =AF43-SUM(AH43:AK43) -> 49545
A44: 31-05-2026 | B44: 88V1106 | C44: Pooja Surendra Singh | D44: 18/11/2024 | E44: F | F44: 31/05/1997 | H44: Surendra Singh | I44: VGLD | J44: Senior Business Development Manager | K44: NEW DELHI | L44: NEW DELHI | N44: GOKPS8099F | O44: 884539469844 | P44: ICICI Bank | Q44: 641201506765 | R44: ICIC0006412 | S44: Pooja Surendra Singh | T44: Indian | U44: 9702926635 | V44: pooja.singh051997@gmail.com | W44: 31 | Y44: =W44-X44 -> 31 | Z44: 23100 | AA44: 0 | AB44: 7810 | AC44: 0 | AD44: 7810 | AE44: =SUM(Z44:AD44) -> 38720 | AF44: =ROUND(AE44/W44*Y44,0) -> 38720 | AI44: 0 | AJ44: 0 | AK44: 0 | AL44: =AF44-SUM(AH44:AK44) -> 38720
A45: 31-05-2026 | B45: 88V1110 | C45: Abhishek Upadhyay | D45: 03/02/2025 | E45: M | F45: 29/05/1995 | H45: Om Prakash Upadhyay | I45: VGLD | J45: Business Development Manager | K45: NEW DELHI | L45: NEW DELHI | N45: AHBPU2618Q | O45: 202275086911 | P45: BANK OF INDIA | Q45: 718110510001483 | R45: BKID0007181 | S45: Abhishek Upadhyay | T45: Indian | U45: 7054311774 | V45: abhiupadhyay170@gmail.com | W45: 31 | Y45: =W45-X45 -> 31 | Z45: 25000 | AA45: 0 | AB45: 7000 | AC45: 0 | AD45: 3000 | AE45: =SUM(Z45:AD45) -> 35000 | AF45: =ROUND(AE45/W45*Y45,0) -> 35000 | AI45: 0 | AJ45: 0 | AK45: 0 | AL45: =AF45-SUM(AH45:AK45) -> 35000
A46: 31-05-2026 | B46: 88V1113 | C46: S Ravi Kumar Dube | D46: 10/03/2025 | E46: M | F46: 31/03/1986 | H46: Shivaji Dube | I46: VGLD | J46: Business Development Manager | K46: NEW DELHI | L46: NEW DELHI | N46: APNPD3887N | O46: 884625587012 | P46: KOTAK MAHINDRA BANK | Q46: 7611821611 | R46: KKBK0007451 | S46: S Ravi Kumar Dube | T46: Indian | U46: 8977310386 | V46: ravidube9@gmail.com | W46: 31 | Y46: =W46-X46 -> 31 | Z46: 25000 | AA46: 0 | AB46: 10500 | AC46: 0 | AD46: 6500 | AE46: =SUM(Z46:AD46) -> 42000 | AF46: =ROUND(AE46/W46*Y46,0) -> 42000 | AI46: 0 | AJ46: 0 | AK46: 0 | AL46: =AF46-SUM(AH46:AK46) -> 42000
A47: 31-05-2026 | B47: 88V1115 | C47: Unnati Singh | D47: 10/06/2025 | E47: F | F47: 09/05/2003 | G47: 46059 | H47: Sunil Singh | I47: VGLD | J47: Content Writer Executive | K47: NEW DELHI | L47: NEW DELHI | N47: PIWPS6408F | O47: 836112758991 | P47: HDFC BANK LTD | Q47: 50100810089015 | R47: HDFC0004754 | S47: Unnati Singh | T47: Indian | U47: 9140913937 | V47: Unnatisng91@gmail.com | W47: 31 | Y47: =W47-X47 -> 31 | Z47: =22000 -> 22000 | AA47: 0 | AB47: =3000-1000 -> 2000 | AC47: 0 | AD47: 0 | AE47: =SUM(Z47:AD47) -> 24000 | AF47: =ROUND(AE47/W47*Y47,0) -> 24000 | AI47: 0 | AJ47: 0 | AK47: 0 | AL47: =AF47-SUM(AH47:AK47) -> 24000
A48: 31-05-2026 | B48: 88V1116 | C48: Neha Parashar | D48: 01/07/2025 | E48: F | F48: 05/05/1996 | H48: Rajesh Mittal | I48: VGLD | J48: Business Development Manager | K48: NEW DELHI | L48: NEW DELHI | N48: FZSPM5215F | O48: 863072150926 | P48: RBL BANK LTD | Q48: 309028265632 | R48: RATN0000532 | S48: Neha Parashar | T48: Indian | U48: 8447661624 | V48: Nehaprshr555@gmail.com | W48: 31 | Y48: =W48-X48 -> 31 | Z48: =24000 -> 24000 | AA48: 0 | AB48: 8500 | AC48: 0 | AD48: 5500 | AE48: =SUM(Z48:AD48) -> 38000 | AF48: =ROUND(AE48/W48*Y48,0) -> 38000 | AI48: 0 | AJ48: 0 | AK48: 0 | AL48: =AF48-SUM(AH48:AK48) -> 38000
A49: 31-05-2026 | B49: 88V1118 | C49: Sagar Varma | D49: 45901 | E49: M | F49: 35542 | J49: Business Development Executive | K49: Chennai | L49: Chennai | P49: State Bank of India | Q49: 33093018131 | R49: SBIN0003308 | S49: Sagar Varma M | T49: Indian | U49: 9176358728 | V49: sagarvarma0280@gmail.com | W49: 31 | Y49: =W49-X49 -> 31 | Z49: 21500 | AA49: 0 | AB49: 0 | AC49: 0 | AD49: 0 | AE49: =SUM(Z49:AD49) -> 21500 | AF49: =ROUND(AE49/W49*Y49,0) -> 21500 | AI49: 1800 | AJ49: 1700 | AK49: 0 | AL49: =AF49-SUM(AH49:AK49)+AG49 -> 18000
A50: 31-05-2026 | B50: 88V1119 | C50: Aisha Sidhika | D50: 45666 | E50: F | F50: 15-03-2000 | J50: Business Development Executive | K50: Chennai | L50: Chennai | P50: PUNJAB NATIONAL BANK | Q50: 4919000100044435 | R50: PUNB0491900 | S50: AISHA SIDHIKA | T50: Indian | U50: 9789002338 | V50: sidhikhaaisha15@gmail.com | W50: 31 | Y50: =W50-X50 -> 31 | Z50: 21300 | AA50: 0 | AB50: 0 | AC50: 0 | AD50: 0 | AE50: =SUM(Z50:AD50) -> 21300 | AF50: =ROUND(AE50/W50*Y50,0) -> 21300 | AI50: 0 | AJ50: 0 | AK50: 0 | AL50: =AF50-SUM(AH50:AK50)+AG50 -> 21300
A51: 31-05-2026 | B51: 88V1121 | C51: Riya | D51: 45925 | E51: F | F51: 24/11/1998 | H51: Jasinta Tirkey | J51: Business Development Executive | K51: Chennai | L51: Chennai | N51: FNDPR1926P | O51: 932282568271 | P51: Canera Bank | Q51: 110043317026 | R51: CNRB0019904 | S51: Riya | T51: Indian | U51: 9289909280 | V51: Riyachh143@gmail.com | W51: 31 | Y51: =W51-X51 -> 31 | Z51: 21100 | AA51: 0 | AB51: 0 | AC51: 0 | AD51: 0 | AE51: =SUM(Z51:AD51) -> 21100 | AF51: =ROUND(AE51/W51*Y51,0) -> 21100 | AI51: 1800 | AJ51: 0 | AK51: 0 | AL51: =AF51-SUM(AH51:AK51) -> 19300
A52: 31-05-2026 | B52: 88V1123 | C52: Renu Aggarwal | E52: F | J52: Student Relationship Manager | N52: AJVPA9580D | O52: 344321182069 | P52: Canera Bank | Q52: 110051564740 | R52: CNRB0000267 | S52: Renu Aggarwal | T52: Indian | U52: 8826856396 | W52: 31 | Y52: =W52-X52 -> 31 | Z52: 28000 | AA52: 0 | AB52: 0 | AC52: 0 | AD52: 0 | AE52: =SUM(Z52:AD52) -> 28000 | AF52: =ROUND(AE52/W52*Y52,0) -> 28000 | AH52: 0 | AI52: 0 | AJ52: 0 | AK52: 0 | AL52: =AF52-SUM(AH52:AK52) -> 28000
A53: 31-05-2026 | B53: 88V1124 | C53: Anil Kumar | D53: 45881 | E53: M | J53: Business Development Manager | K53: Delhi | L53: Delhi | N53: EIRPK6138N | O53: 591717287710 | P53: Kotak MahiNDRA BANK | Q53: 4750329411 | R53: KKBK0000203 | S53: Anil Kumar | T53: Indian | U53: 9005654216 | V53: anil@vglearningdestination.com | W53: 31 | X53: 3 | Y53: =W53-X53 -> 28 | Z53: 35000 | AA53: 0 | AB53: 5000 | AD53: 4000 | AE53: =SUM(Z53:AD53) -> 44000 | AF53: =ROUND(AE53/W53*Y53,0) -> 39742 | AG53: 1800 | AH53: 0 | AI53: 0 | AJ53: 0 | AK53: 0 | AL53: =AF53-SUM(AH53:AK53)+AG53 -> 41542
A54: 31-05-2026 | B54: 88V1122 | C54: Asad Ansari | D54: 45759 | E54: M | F54: 23-12-2000 | G54: Also Leave in May, Confirm by porikhit | J54: Business Development Manager | N54: DJCPA3887H | O54: 493673568805 | P54: HDFC BANK LTD | Q54: 50100749133206 | R54: HDFC0001236 | S54: Asad Ansari | T54: Indian | U54: 7982177523 | V54: mdasadansari2000@gmail.com | W54: 31 | X54: =LOP!R69 -> 23 | Y54: =W54-X54 -> 8 | Z54: 43560 | AA54: 0 | AB54: 4737 | AC54: 0 | AD54: 3475 | AE54: =SUM(Z54:AD54) -> 51772 | AF54: =ROUND(AE54/W54*Y54,0) -> 13361 | AH54: 0 | AI54: 0 | AJ54: 0 | AK54: 0 | AL54: =AF54-SUM(AH54:AK54) -> 13361
A55: 31-05-2026 | B55: 88V1125 | C55: Lakshminarayan Agrawal | D55: 45912 | E55: M | F55: 35193 | H55: Jagdish Prasad | J55: Business Development Manager | K55: Lucknow | L55: Lucknow | N55: CGSPA0647K | O55: 766030561836 | P55: Yes Bank | Q55: 7294000000049 | R55: YESB0000072 | S55: Lakshminarayan Agrawal | T55: Indian | U55: 8630738106 | V55: lnagrawal005@gmail.com | W55: 31 | Y55: =W55-X55 -> 31 | Z55: 24000 | AA55: 0 | AB55: 4000 | AD55: 4000 | AE55: =SUM(Z55:AD55) -> 32000 | AF55: =ROUND(AE55/W55*Y55,0) -> 32000 | AH55: 0 | AI55: 0 | AJ55: 0 | AK55: 0 | AL55: =AF55-SUM(AH55:AK55) -> 32000
A56: 31-05-2026 | B56: 88V1127 | C56: Deep Ghatak | D56: 15-04-2025 | E56: M | F56: 31635 | H56: Prasanta Kumar Ghatak | J56: Business Development Manager | K56: Chennai | L56: Chennai | N56: AITPG5879Q | O56: 392853690406 | P56: HSBC Bank | Q56: 74282930006 | R56: HSBC0560002 | S56: Deep Ghatak | T56: Indian | U56: 8929230328 | V56: deep.ghatak@zohomail.in | W56: 31 | Y56: =W56-X56 -> 31 | Z56: 23400 | AB56: 6000 | AD56: =32000-29400 -> 2600 | AE56: =SUM(Z56:AD56) -> 32000 | AF56: =ROUND(AE56/W56*Y56,0) -> 32000 | AI56: 0 | AJ56: 0 | AK56: 0 | AL56: =AF56-SUM(AH56:AK56) -> 32000
A57: 31-05-2026 | B57: 88V1126 | C57: Abhishek Verma | D57: 16-03-2026 | E57: M | F57: 35076 | H57: Ravi Kumar Verma | J57: Business Development Manager | K57: Delhi | L57: Delhi | N57: BFNPV5003B | O57: 918480195476 | P57: Bank of Baroda | Q57: 79990100007448 | R57: BARB0VJHAJI | S57: Abhishek Verma | T57: Indian | U57: 9337818142 | V57: abhishekverma683@gmail.com | W57: 31 | Y57: =W57-X57 -> 31 | Z57: 24500 | AB57: 10250 | AD57: 10250 | AE57: =SUM(Z57:AD57) -> 45000 | AF57: =ROUND(AE57/W57*Y57,0) -> 45000 | AL57: =AF57-SUM(AH57:AK57) -> 45000
A58: 31-05-2026 | B58: 88V1128 | C58: Lubaina Mirza | D58: 16-04-2026 | E58: M | F58: 38390 | H58: Zaheer Ali Mirza | J58: Business Development Manager | K58: Mumbai | L58: Mumbai | N58: JFWPM3058E | O58: 793748330718 | P58: Axis Bank | Q58: 925010038124759 | R58: UTIB0001621 | S58: Lubaina Mirza | T58: Indian | U58: 9867215089 | V58: lubaina@vglearningdestination.com | W58: 31 | X58: 0 | Y58: 31 | Z58: 21500 | AB58: 3500 | AD58: 0 | AE58: 25000 | AF58: =ROUND(AE58/W58*Y58,0) -> 25000 | AL58: =AF58-SUM(AH58:AK58) -> 25000
AL59: =AF59-SUM(AH59:AK59) -> 0
B60: =COUNTA(B5:B59) -> 54 | G60: =COUNTA(G5:G55) -> 2 | T60: TOTAL | Z60: =SUM(Z5:Z59) -> 1685341 | AA60: =SUM(AA5:AA51) -> 0 | AB60: =SUM(AB5:AB59) -> 625748 | AC60: =SUM(AC5:AC51) -> 0 | AD60: =SUM(AD5:AD59) -> 528074 | AE60: =SUM(AE5:AE59) -> 2839163 | AF60: =SUM(AF5:AF59) -> 2786441 | AG60: =SUM(AG5:AG55) -> 3010 | AH60: =SUM(AH5:AH59) -> 85212.647 | AI60: =SUM(AI5:AI59) -> 9000 | AJ60: =SUM(AJ5:AJ51) -> 2215 | AK60: =SUM(AK5:AK51) -> 0 | AL60: =SUM(AL5:AL59) -> 2693023.4 | AN60: =AL60+AI60+AH60 -> 2787236 | AP60: =AL60-2860830 -> -167806.65
B63: Pooja
AI64: =AI60*2 -> 18000
AF65: Salary | AG65: =AF60+AG60 -> 2789451
AF66: Incentive of November | AG66: 0
AF67: TDS | AG67: =AH60 -> 85212.647
AF68: PF | AG68: =AI60 -> 9000
AF69: Salary Payable | AH69: =AG65-AG66-AG67-AG68 -> 2695238.4
AG71: =AL60 -> 2693023.4
AG73: =AG69-AG71 -> -2693023.4

Sheet LOP
A1: May_2026 Attendance Summary - 01.05.2026 To 31.05.2026
A2: Sr. No. | B2: Assigned to | C2: Employee | D2: UID | E2: Employee Name | F2: Total Working days | G2: Half Day | H2: Absent | I2: Late upto 10:30 | J2: Late more than half an hour | K2: LOP for Late | L2: Holiday working | M2: Remarks | N2: CL | O2: SL | P2: PL | Q2: Optional Holiday | R2: LOP | S2: Punching Missing | T2: Work from home
A3: 1 | B3: Gulshan | C3: 88 | D3: 88A1003 | E3: Gulshan | F3: 31 | G3: - | H3: - | I3: - | J3: - | K3: -
A4: 2 | B4: Ajay Saxena | C4: 88 | D4: 88A1004 | E4: AJAY SAXENA | F4: 31 | G4: 0 | H4: 1 | I4: 0 | J4: 0 | K4: 0 | N4: 0 | O4: 1 | P4: 0 | Q4: 0 | R4: 0
A5: 3 | B5: Manazir | C5: VGLD | D5: 88E1114 | E5: Pooja | F5: 31 | G5: 0 | H5: 0 | I5: 0 | J5: 0 | K5: 0 | N5: 0 | O5: 0 | P5: 0 | Q5: 0 | R5: 0
A6: 4 | B6: PRIYA MADAN | C6: VGLD | D6: 88E1115 | E6: Divya Thakur | F6: 31 | G6: 0 | H6: 2 | I6: 0 | J6: 1 | K6: 0 | M6: Late upto 10:30= 07 | N6: 0 | O6: 0 | P6: 0 | Q6: 0 | R6: 2 | S6: 1
A7: 5 | B7: Ubaid | C7: VGLD | D7: 88E1116 | E7: Babita | F7: 31 | G7: 0 | H7: 15 | I7: 0 | J7: 0 | K7: 0 | N7: 0 | O7: 0 | P7: 1 | Q7: 1 | R7: 13
A8: 6 | B8: Arpit Acharya | C8: VGLD | D8: 88E1120 | E8: Kunal Kashyap | F8: 31 | G8: - | H8: - | I8: - | J8: - | K8: - | N8: 0 | O8: 0 | P8: 0 | Q8: 0 | R8: 0
A9: 7 | B9: Ajay Saxena | C9: VGLD | D9: 88E1121 | E9: Shivam | F9: 31 | G9: 0 | H9: 1 | I9: 2 | J9: 0 | K9: 0 | N9: 0 | O9: 0 | P9: 1 | Q9: 0 | R9: 0
A10: 8 | B10: Arpit Acharya | C10: VGLD | D10: 88E1122 | E10: Shahwaiz Ajmali | F10: 31 | G10: 2 | H10: 6 | I10: 0 | J10: 0 | K10: 0 | N10: 0.5 | O10: 0.5 | P10: 2 | Q10: 1 | R10: 3
A11: 9 | B11: Manazir | C11: VGLD | D11: 88E1124 | E11: Dev Karan | F11: 31 | G11: 4 | H11: 0 | I11: 2 | J11: 0 | K11: 0 | M11: Late upto 10:30= 19 | N11: 0 | O11: 0 | P11: 0 | Q11: 0 | R11: 2
A12: 10 | B12: PINKU KUMAR | C12: VGLD | D12: 88E1125 | E12: Sakshi | F12: 31 | G12: 0 | H12: 1 | I12: 0 | J12: 0 | K12: 0 | N12: 1 | O12: 0 | P12: 0 | Q12: 0 | R12: 0
A13: 11 | B13: Ajay Saxena | C13: VGLD | D13: 88E1126 | E13: Juhi Kumari | F13: 31 | G13: 2 | H13: 3 | I13: 0 | J13: 0 | K13: 0 | M13: Late upto 10:30= 06 | N13: 1 | O13: 1 | P13: 1 | Q13: 0 | R13: 1 | S13: 1
A14: 12 | B14: Arpit Acharya | C14: VGLD | D14: 88E1127 | E14: Abdul | F14: 31 | G14: 4 | H14: 3 | I14: 0 | J14: 0 | K14: 0 | M14: Late upto 10:30= 05 | N14: 0.5 | O14: 0 | P14: 1 | Q14: 1 | R14: 2.5 | S14: 1
A15: 13 | B15: Ajay Saxena | C15: VGLD | D15: 88E1129 | E15: Akash | F15: 31 | G15: 1 | H15: 0 | I15: 3 | J15: 0 | K15: 0 | N15: 0.5 | O15: 0 | P15: 0 | Q15: 0 | R15: 0
A16: 14 | B16: PINKU KUMAR | C16: VGLD | D16: 88E1132 | E16: Khushi Kumari | F16: 31 | G16: 0 | H16: 2 | I16: 0 | J16: 0 | K16: 0 | N16: 1 | O16: 1 | P16: 0 | Q16: 0 | R16: 0
A17: 15 | B17: Raj Kamal | C17: 88 | D17: 88G1001 | E17: Rashi Gupta | F17: 31 | G17: - | H17: - | I17: - | J17: - | K17: - | N17: 0 | O17: 0 | P17: 1 | Q17: 0 | R17: 0
A18: 16 | B18: Raj Kamal | C18: 88 | D18: 88G1003 | E18: RAJ | F18: 31 | G18: 1 | H18: 5 | I18: 0 | J18: 0 | K18: 0 | N18: 0.5 | O18: 0 | P18: 5 | Q18: 0 | R18: 0
A19: 17 | B19: Gulshan | C19: 88 | D19: 88G1011 | E19: Meenakshi Gosai | F19: 31 | G19: - | H19: - | I19: - | J19: - | K19: -
A20: 18 | B20: Gulshan | C20: 88 | D20: 88G1012 | E20: Deepa Chandnani | F20: 31 | G20: - | H20: - | I20: - | J20: - | K20: -
A21: 19 | B21: Ubaid | C21: 88 | D21: 88G1014 | E21: Nidhi | F21: 31 | G21: 1 | H21: 3 | I21: 0 | J21: 0 | K21: 0 | M21: Late upto 10:30= 22 | N21: 0.5 | O21: 0.5 | P21: 1 | Q21: 0 | R21: 1.5
A22: 20 | B22: Raj Kamal | C22: 88 | D22: 88G1022 | E22: SHALINI | F22: 31 | G22: - | H22: - | I22: - | J22: - | K22: -
A23: 21 | B23: Ajay Saxena | C23: 88 | D23: 88G1041 | E23: VIKAS PAWAR | F23: 31 | G23: 0 | H23: 1 | I23: 1 | J23: 0 | K23: 0 | N23: 0 | O23: 1 | P23: 0 | Q23: 0 | R23: 0
A24: 22 | B24: Gulshan | C24: 88 | D24: 88G1064 | E24: Maheen Ajmali | F24: 31 | G24: - | H24: - | I24: - | J24: - | K24: - | N24: 0 | O24: 0 | P24: 1 | Q24: 1 | R24: 0
A25: 23 | B25: PINKU KUMAR | C25: 88 | D25: 88G1078 | E25: PINKU KUMAR | F25: 31 | G25: 0 | H25: 0 | I25: 0 | J25: 0 | K25: 0 | N25: 0 | O25: 0 | P25: 0 | Q25: 0 | R25: 0
A26: 24 | B26: Arpit Acharya | C26: 88 | D26: 88G1087 | E26: ARPIT ACHARYA | F26: 31 | G26: - | H26: - | I26: - | J26: - | K26: - | N26: 1 | O26: 0 | P26: 0 | Q26: 0 | R26: 0
A27: 25 | B27: Self | C27: 88 | D27: 88V1003 | E27: RACHNA AJMANI | F27: 31 | G27: 2 | H27: 2 | I27: 3 | J27: 0 | K27: 0 | M27: Late upto 10:30= 19 | N27: 0.5 | O27: 0.5 | P27: 1 | Q27: 0 | R27: 1
A28: 26 | B28: Self | C28: 88 | D28: 88V1006 | E28: SHALU | F28: 31 | G28: - | H28: - | I28: - | J28: - | K28: -
A29: 27 | B29: Gulshan | C29: 88 | D29: 88V1012 | E29: Sandeep Maurya | F29: 31 | G29: - | H29: - | I29: - | J29: - | K29: -
A30: 28 | B30: PRIYA MADAN | C30: 88 | D30: 88V1018 | E30: PRIYA MADAN | F30: 31 | G30: 1 | H30: 5 | I30: 1 | J30: 0 | K30: 0 | M30: Late upto 10:30= 16 | N30: 0.5 | O30: 0 | P30: 1 | Q30: 0 | R30: 4 | S30: Consider 2 days as work from home then 20% salary will deduct
A31: 29 | B31: MONIKA | C31: 88 | D31: 88V1024 | E31: MONIKA | F31: 31 | G31: 2 | H31: 0 | I31: 0 | J31: 0 | K31: 0 | N31: 0.5 | O31: 0.5 | P31: 0 | Q31: 0 | R31: 0
A32: 30 | B32: Manazir | C32: 88 | D32: 88V1029 | E32: SANDEEP GUPTA | F32: 31 | G32: 1 | H32: 2 | I32: 1 | J32: 1 | K32: 0 | N32: 0.5 | O32: 0.5 | P32: 2 | Q32: 0 | R32: 0
A33: 31 | B33: Ubaid | C33: 88 | D33: 88V1032 | E33: UBAID | F33: 31 | G33: 0 | H33: 1 | I33: 0 | J33: 0 | K33: 0 | M33: Late upto 10:30= 21 | N33: 0 | O33: 0 | P33: 1 | Q33: 0 | R33: 0 | S33: 2
A34: 32 | B34: Arpit Acharya | C34: 88 | D34: 88V1033 | E34: JYOTI SINGH | F34: 31 | G34: - | H34: - | I34: - | J34: - | K34: - | N34: 0 | O34: 0.5 | P34: 0 | Q34: 0 | R34: 0
A35: 33 | B35: Manazir | C35: 88 | D35: 88V1035 | E35: SUGANDHA | F35: 31 | G35: 0 | H35: 1 | I35: 0 | J35: 0 | K35: 0 | M35: Late upto 10:30= 01 | N35: 0.5 | O35: 0.5 | P35: 0 | Q35: 0 | R35: 0
A36: 34 | B36: PORIKHIT DAS | C36: 88 | D36: 88V1047 | E36: PORIKHIT DAS | F36: 31 | G36: 0 | H36: 7 | I36: 2 | J36: 0 | K36: 0 | M36: Late upto 10:30= 13 | N36: 0.5 | O36: 0.5 | P36: 3 | Q36: 1 | R36: 2
A37: 35 | B37: Manazir | C37: 88 | D37: 88V1050 | E37: MANAZIR | F37: 31 | G37: 0 | H37: 1 | I37: 0 | J37: 0 | K37: 0 | M37: Late upto 10:30= 13 | N37: 0 | O37: 0 | P37: 0 | Q37: 1 | R37: 0 | S37: 2
A38: 36 | B38: Manazir | C38: 88 | D38: 88V1051 | E38: SOHRAB HAIDAR | F38: 31 | G38: 0 | H38: 2 | I38: 0 | J38: 0 | K38: 0 | M38: Late upto 10:30= 11 | N38: 0 | O38: 1 | P38: 0 | Q38: 1 | R38: 0
A39: 37 | B39: Hyderabad | C39: 88 | D39: 88V1052 | E39: Anita Dubey | F39: 31 | G39: - | H39: - | I39: - | J39: - | K39: -
A40: 38 | B40: Manmohan | C40: 88 | D40: 88V1057 | E40: Aman Singh | F40: 31 | G40: - | H40: - | I40: - | J40: - | K40: -
A41: 39 | B41: Mumbai | C41: 88 | D41: 88V1062 | E41: Parth Saraiyan | F41: 31 | G41: 0 | H41: 1 | I41: 0 | J41: 0 | K41: 0 | N41: 0 | O41: 1 | P41: 0 | Q41: 0 | R41: 0
A42: 40 | B42: Hyderabad | C42: 88 | D42: 88V1067 | E42: Sangeeta | F42: 31 | G42: - | H42: - | I42: - | J42: - | K42: -
A43: 41 | B43: Ajay Saxena | C43: 88 | D43: 88V1076 | E43: ALOK SHRIVASTAVA | F43: 31 | G43: 1 | H43: 0 | I43: 1 | J43: 0 | K43: 0 | N43: 0.5 | O43: 0 | P43: 0 | Q43: 0 | R43: 0 | S43: 2
A44: 42 | B44: Ubaid | C44: 88 | D44: 88V1077 | E44: Aman Kumar | F44: 31 | G44: 1 | H44: 2 | I44: 2 | J44: 0 | K44: 0 | N44: 0 | O44: 0.5 | P44: 1 | Q44: 1 | R44: 0
A45: 43 | B45: PRIYA MADAN | C45: 88 | D45: 88V1078 | E45: Ishant Garg | F45: 31 | G45: - | H45: - | I45: - | J45: - | K45: -
A46: 44 | B46: Manmohan | C46: 88 | D46: 88V1085 | E46: Manmohan Rawat | F46: 31 | G46: 0 | H46: 0 | I46: 0 | J46: 0 | K46: 0 | N46: 0 | O46: 0 | P46: 0 | Q46: 0 | R46: 0
A47: 45 | B47: Hyderabad | C47: 88 | D47: 88V1086 | E47: Kyvalya | F47: 31 | G47: - | H47: - | I47: - | J47: - | K47: -
A48: 46 | B48: Manmohan | C48: 88 | D48: 88V1089 | E48: Chetan Bisht | F48: 31 | G48: 0 | H48: 1 | I48: 0 | J48: 0 | K48: 0 | N48: 0 | O48: 0 | P48: 1 | Q48: 0 | R48: 0
A49: 47 | B49: Manmohan | C49: 88 | D49: 88V1090 | E49: Nitin Parashar | F49: 31 | G49: 1 | H49: 2 | I49: 0 | J49: 0 | K49: 0 | N49: 0 | O49: 0.5 | P49: 2 | Q49: 0 | R49: 0
A50: 48 | B50: MONIKA | C50: 88 | D50: 88V1091 | E50: Sanjay tewari | F50: 31 | G50: 1 | H50: 2 | I50: 2 | J50: 0 | K50: 0 | M50: Late upto 10:30= 21 | N50: 0.5 | O50: 0.5 | P50: 1 | Q50: 0 | R50: 0.5
A51: 49 | B51: Kolkata | C51: 88 | D51: 88V1092 | E51: Rajesh Machhiya | F51: 31 | G51: - | H51: - | I51: - | J51: - | K51: -
A52: 50 | B52: Ajay Saxena | C52: 88 | D52: 88V1098 | E52: Unnati Sharma | F52: 31 | G52: 0 | H52: 2 | I52: 2 | J52: 0 | K52: 0 | M52: Late upto 10:30= 14 | N52: 0.5 | O52: 0.5 | P52: 1 | Q52: 0 | R52: 0
A53: 51 | B53: PORIKHIT DAS | C53: 88 | D53: 88V1100 | E53: Hrithik Katyal | F53: 31 | G53: 0 | H53: 2 | I53: 0 | J53: 0 | K53: 0 | M53: Late upto 10:30= 17 | N53: 0 | O53: 1 | P53: 1 | Q53: 0 | R53: 0
A54: 52 | B54: Mumbai | C54: 88 | D54: 88V1105 | E54: Naved Chauhan | F54: 31 | G54: 0 | H54: 0 | I54: 0 | J54: 0 | K54: 0 | N54: 0 | O54: 0 | P54: 0 | Q54: 0 | R54: 0
A55: 53 | B55: Mumbai | C55: 88 | D55: 88V1106 | E55: Pooja Singh | F55: 31 | G55: 0 | H55: 4 | I55: 0 | J55: 0 | K55: 0 | N55: 0 | O55: 0 | P55: 4 | Q55: 0 | R55: 0
A56: 54 | B56: Jaipur | C56: 88 | D56: 88V1110 | E56: Abhishek | F56: 31 | G56: - | H56: - | I56: - | J56: - | K56: -
A57: 55 | B57: Lucknow | C57: 88 | D57: 88V1113 | E57: Ravi Duvey | F57: 31 | G57: 0 | H57: 1 | I57: 0 | J57: 0 | K57: 0 | N57: 0 | O57: 1 | P57: 0 | Q57: 0 | R57: 0
A58: 56 | B58: PINKU KUMAR | C58: 88 | D58: 88V1115 | E58: Unnati Singh | F58: 31 | G58: 0 | H58: 3 | I58: 1 | J58: 0 | K58: 0 | M58: Late upto 10:30= 01 | N58: 0.5 | O58: 0 | P58: 1 | Q58: 0 | R58: 1.5 | S58: 1
A59: 57 | B59: PRIYA MADAN | C59: 88 | D59: 88V1116 | E59: Neha Parasar | F59: 31 | G59: 1 | H59: 2 | I59: 0 | J59: 1 | K59: 0 | N59: 0.5 | O59: 0 | P59: 2 | Q59: 0 | R59: 0
A60: 58 | B60: Ajay Saxena | C60: HOE | D60: 88H1028 | E60: Suneaba | F60: 31
A61: 59 | B61: Ajay Saxena | C61: 88 | D61: 88H1088 | E61: Renu Aggarwal | F61: 31 | G61: 0 | H61: 0 | I61: 0 | J61: 0 | K61: 0 | N61: 0 | O61: 0 | P61: 0 | Q61: 0 | R61: 0
A62: 61 | B62: Chennai | C62: 88 | D62: 88V1119 | E62: Aisha Sidhika | F62: 31 | G62: - | H62: 1 | I62: - | J62: - | K62: -
A63: 62 | B63: Chennai | C63: 88 | D63: 88V1121 | E63: Riya Chhabra | F63: 31 | G63: - | H63: 1 | I63: - | J63: - | K63: -
A64: 63 | B64: Chennai | C64: 88 | D64: 88V1121 | E64: Sagar Varma | F64: 31 | G64: - | H64: - | I64: - | J64: - | K64: -
A65: 64 | B65: Ajay Saxena | C65: HOE | D65: 13 | E65: SUNIL | F65: 31
A66: 65 | B66: Gulshan | C66: 88 | D66: 88G1013 | E66: Jyoti Pal | F66: 31 | G66: - | H66: - | I66: - | J66: - | K66: - | N66: 0 | O66: 0 | P66: 2 | Q66: 0 | R66: 0
A67: 66 | B67: Gulshan | C67: 88 | E67: Roshan | F67: 31 | G67: - | H67: - | I67: - | J67: - | K67: -
A68: 67 | B68: PORIKHIT DAS | C68: 88 | D68: 88V1154 | E68: Anil | F68: 31 | G68: 0 | H68: 10 | I68: 0 | J68: 0 | K68: 0 | M68: Late upto 10:30= 11 | N68: 0 | O68: 1 | P68: 2 | Q68: 1 | R68: 6 | S68: 3 Days also approved by Narayn Sir
A69: 68 | B69: PORIKHIT DAS | C69: 88 | D69: 88V1175 | E69: Asad | F69: 31 | G69: 0 | H69: 23 | I69: 0 | J69: 0 | K69: 0 | N69: 0 | O69: 0 | P69: 0 | Q69: 0 | R69: 23
A70: 69 | B70: Jaipur | C70: 88 | E70: Lakshmi Narayan Agrawal | F70: 31 | G70: - | H70: - | I70: - | J70: - | K70: -
A71: 70 | B71: Gulshan | C71: 88 | D71: 88G1008 | E71: Mohan Kumar | F71: 31 | G71: - | H71: - | I71: - | J71: - | K71: -
A72: 71 | B72: Gulshan | C72: 88 | E72: Babulal | F72: 31 | G72: - | H72: - | I72: - | J72: - | K72: -
A73: 72 | B73: Manmohan | C73: 88 | E73: Abhishek Verma | F73: 31 | G73: 0 | H73: 2 | I73: 0 | J73: 0 | K73: 0 | N73: 1 | O73: 0 | P73: 1 | Q73: 0 | R73: 0
A74: 73 | B74: Arpit Acharya | C74: VGLD | D74: 88V1143 | E74: Krishna | F74: 31
A75: 74 | B75: Mumbai | C75: 88 | E75: Lubaina Mirza | F75: 31 | G75: 0 | H75: 0 | I75: 0 | J75: 0 | K75: 0 | N75: 0 | O75: 0 | P75: 0 | Q75: 0 | R75: 0
A76: 75 | B76: Kolkata | C76: 88 | E76: Deep Ghatak | F76: 31 | G76: 1 | H76: - | I76: - | J76: - | K76: - | N76: 0 | O76: 0.5 | P76: 0 | Q76: 0 | R76: 0
A77: 76 | B77: Ajay Saxena | C77: HOE | D77: 88H1180 | E77: Abhishek | F77: 31 | G77: 0 | H77: 20 | I77: 0 | J77: 0 | K77: 0 | M77: House of Elorra | R77: 20
A78: 77

Sheet Non HDFC 2
A1: Transaction_Reference_No | B1: Beneficiary_Name | C1: Amount | D1: Remitter_Details | E1: Debit_Account_System | F1: Originator_Of_Remittance | G1: Email_ID_Mobile_No
A2: 1 | B2: Narayan Kasat | C2: =VLOOKUP(B2,'Draft-Paysheet May 2026'!$C$4:$AL$51,37,0) -> #REF! | D2: 88ACADEMICS INDIA PRIVATE LIMITED | F2: 88ACADEMICS INDIA PRIVATE LIMITED | G2: 9891054411
A3: 2 | B3: Babu Lal | C3: =VLOOKUP(B3,'Draft-Paysheet May 2026'!$C$4:$AL$51,37,0) -> #REF! | D3: 88ACADEMICS INDIA PRIVATE LIMITED | F3: 88ACADEMICS INDIA PRIVATE LIMITED | G3: 9873030060
A4: 3 | B4: Gulshan | C4: =VLOOKUP(B4,'Draft-Paysheet May 2026'!$C$4:$AL$51,37,0) -> #REF! | D4: 88ACADEMICS INDIA PRIVATE LIMITED | F4: 88ACADEMICS INDIA PRIVATE LIMITED | G4: 9717013679
A5: 4 | B5: Rashi Gupta | C5: =VLOOKUP(B5,'Draft-Paysheet May 2026'!$C$4:$AL$51,37,0) -> #REF! | D5: 88ACADEMICS INDIA PRIVATE LIMITED | F5: 88ACADEMICS INDIA PRIVATE LIMITED | G5: 9654365202
A6: 5 | B6: Raj Kamal Sharma | C6: =VLOOKUP(B6,'Draft-Paysheet May 2026'!$C$4:$AL$51,37,0) -> #REF! | D6: 88ACADEMICS INDIA PRIVATE LIMITED | F6: 88ACADEMICS INDIA PRIVATE LIMITED | G6: 9968722755
A7: 6 | B7: Roshan Sharma | C7: =VLOOKUP(B7,'Draft-Paysheet May 2026'!$C$4:$AL$51,37,0) -> #REF! | D7: 88ACADEMICS INDIA PRIVATE LIMITED | F7: 88ACADEMICS INDIA PRIVATE LIMITED | G7: 9911811713
A8: 7 | B8: Mohan Kumar | C8: =VLOOKUP(B8,'Draft-Paysheet May 2026'!$C$4:$AL$51,37,0) -> #N/A | D8: 88ACADEMICS INDIA PRIVATE LIMITED | F8: 88ACADEMICS INDIA PRIVATE LIMITED | G8: 9540409376
A9: 8 | B9: Meenakshi Gosai | C9: =VLOOKUP(B9,'Draft-Paysheet May 2026'!$C$4:$AL$51,37,0) -> #REF! | D9: 88ACADEMICS INDIA PRIVATE LIMITED | F9: 88ACADEMICS INDIA PRIVATE LIMITED | G9: 7042668809
A10: 9 | B10: Deepa Chandnani | C10: ='Draft-Paysheet May 2026'!AL13 -> 42000 | D10: 88ACADEMICS INDIA PRIVATE LIMITED | F10: 88ACADEMICS INDIA PRIVATE LIMITED | G10: 9873452523
A11: 10 | B11: Nidhi Gupta | C11: =VLOOKUP(B11,'Draft-Paysheet May 2026'!$C$4:$AL$51,37,0) -> #REF! | D11: 88ACADEMICS INDIA PRIVATE LIMITED | F11: 88ACADEMICS INDIA PRIVATE LIMITED | G11: 9958127672
A12: 11 | B12: Shalini Sharma | C12: =VLOOKUP(B12,'Draft-Paysheet May 2026'!$C$4:$AL$51,37,0) -> #REF! | D12: 88ACADEMICS INDIA PRIVATE LIMITED | F12: 88ACADEMICS INDIA PRIVATE LIMITED | G12: 9999868854
A13: 12 | B13: Vikas Panwar | C13: =VLOOKUP(B13,'Draft-Paysheet May 2026'!$C$4:$AL$51,37,0) -> #REF! | D13: 88ACADEMICS INDIA PRIVATE LIMITED | F13: 88ACADEMICS INDIA PRIVATE LIMITED | G13: 8755629335
A14: 13 | B14: Maheen Ajmali | C14: =VLOOKUP(B14,'Draft-Paysheet May 2026'!$C$4:$AL$51,37,0) -> #REF! | D14: 88ACADEMICS INDIA PRIVATE LIMITED | F14: 88ACADEMICS INDIA PRIVATE LIMITED | G14: 9873907268
A15: 14 | B15: Neelansh Pandey | C15: =VLOOKUP(B15,'Draft-Paysheet May 2026'!$C$4:$AL$51,37,0) -> #N/A | D15: 88ACADEMICS INDIA PRIVATE LIMITED | F15: 88ACADEMICS INDIA PRIVATE LIMITED | G15: 9696472351
A16: 15 | B16: Arpit Acharya | C16: =VLOOKUP(B16,'Draft-Paysheet May 2026'!$C$4:$AL$51,37,0) -> #REF! | D16: 88ACADEMICS INDIA PRIVATE LIMITED | F16: 88ACADEMICS INDIA PRIVATE LIMITED | G16: 8273317514
A17: 16 | B17: Sandeep Maurya | C17: =VLOOKUP(B17,'Draft-Paysheet May 2026'!$C$4:$AL$51,37,0) -> #REF! | D17: 88ACADEMICS INDIA PRIVATE LIMITED | F17: 88ACADEMICS INDIA PRIVATE LIMITED | G17: 8268890388
A18: 17 | B18: Priya Madan | C18: =VLOOKUP(B18,'Draft-Paysheet May 2026'!$C$4:$AL$51,37,0) -> #REF! | D18: 88ACADEMICS INDIA PRIVATE LIMITED | F18: 88ACADEMICS INDIA PRIVATE LIMITED | G18: 7379258598
A19: 18 | B19: Monika Dhingra | C19: =VLOOKUP(B19,'Draft-Paysheet May 2026'!$C$4:$AL$51,37,0) -> #REF! | D19: 88ACADEMICS INDIA PRIVATE LIMITED | F19: 88ACADEMICS INDIA PRIVATE LIMITED | G19: 9654797629
A20: 19 | B20: Jyoti Singh | C20: =VLOOKUP(B20,'Draft-Paysheet May 2026'!$C$4:$AL$51,37,0) -> #REF! | D20: 88ACADEMICS INDIA PRIVATE LIMITED | F20: 88ACADEMICS INDIA PRIVATE LIMITED | G20: 9873040788
A21: 20 | B21: Sugandha Bhatnagar | C21: =VLOOKUP(B21,'Draft-Paysheet May 2026'!$C$4:$AL$51,37,0) -> #REF! | D21: 88ACADEMICS INDIA PRIVATE LIMITED | F21: 88ACADEMICS INDIA PRIVATE LIMITED | G21: 7982537821
A22: 21 | B22: Porikhit Das | C22: =VLOOKUP(B22,'Draft-Paysheet May 2026'!$C$4:$AL$51,37,0) -> #REF! | D22: 88ACADEMICS INDIA PRIVATE LIMITED | F22: 88ACADEMICS INDIA PRIVATE LIMITED | G22: 8534999427
... A41: 40 | B41: Sagar Varma | C41: =VLOOKUP(B41,'Draft-Paysheet May 2026'!$C$4:$AL$51,37,0) -> #REF! | D41: 88ACADEMICS INDIA PRIVATE LIMITED | F41: 88ACADEMICS INDIA PRIVATE LIMITED | G41: 7054311774
A42: 41 | B42: Aisha Sidhika | C42: =VLOOKUP(B42,'Draft-Paysheet May 2026'!$C$4:$AL$51,37,0) -> #REF! | D42: 88ACADEMICS INDIA PRIVATE LIMITED | F42: 88ACADEMICS INDIA PRIVATE LIMITED
A43: 42 | B43: Riya | C43: =VLOOKUP(B43,'Draft-Paysheet May 2026'!$C$4:$AL$51,37,0) -> #REF! | D43: 88ACADEMICS INDIA PRIVATE LIMITED | F43: 88ACADEMICS INDIA PRIVATE LIMITED
B45: Total | C45: =SUM(C2:C44) -> #REF!

Sheet New HDFC
A2: SL_NO | B2: Employee Code | C2: Employee Name | D2: Account no | E2: AMOUNT
A4: 1 | B4: 88A1004 | C4: Ajay Kumar Saxena | D4: =VLOOKUP(C4,'Draft-Paysheet May 2026'!$C$4:$Q$51,15,0) -> 50100446028500 | E4: =VLOOKUP(C4,'Draft-Paysheet May 2026'!$C$4:$AL$51,37,0) -> #REF!
A5: 2 | B5: 88G1004 | C5: Simran Kumari Arora | D5: =VLOOKUP(C5,'Draft-Paysheet May 2026'!$C$4:$Q$51,15,0) -> #N/A | E5: =VLOOKUP(C5,'Draft-Paysheet May 2026'!$C$4:$AL$51,37,0) -> #N/A
A6: 3 | B6: 88G1013 | C6: Jyoti Pal | D6: =VLOOKUP(C6,'Draft-Paysheet May 2026'!$C$4:$Q$51,15,0) -> 50100151532802 | E6: =VLOOKUP(C6,'Draft-Paysheet May 2026'!$C$4:$AL$51,37,0) -> #REF!
A7: 4 | B7: 88G1032 | C7: Kiran Pathak | D7: =VLOOKUP(C7,'Draft-Paysheet May 2026'!$C$4:$Q$51,15,0) -> #N/A | E7: =VLOOKUP(C7,'Draft-Paysheet May 2026'!$C$4:$AL$51,37,0) -> #N/A
A8: 5 | B8: 88G1074 | C8: Rakesh Singh Rawat | D8: =VLOOKUP(C8,'Draft-Paysheet May 2026'!$C$4:$Q$51,15,0) -> #N/A | E8: =VLOOKUP(C8,'Draft-Paysheet May 2026'!$C$4:$AL$51,37,0) -> #N/A
A9: 6 | B9: 88G1078 | C9: Pinku Kumar | D9: =VLOOKUP(C9,'Draft-Paysheet May 2026'!$C$4:$Q$51,15,0) -> 50100754820324 | E9: =VLOOKUP(C9,'Draft-Paysheet May 2026'!$C$4:$AL$51,37,0) -> #REF!
A10: 7 | B10: 88V1003 | C10: Rachna Ajmani | D10: =VLOOKUP(C10,'Draft-Paysheet May 2026'!$C$4:$Q$51,15,0) -> 50100067622091 | E10: =VLOOKUP(C10,'Draft-Paysheet May 2026'!$C$4:$AL$51,37,0) -> #REF!
A11: 8 | B11: 88V1006 | C11: Shalu Gandhi | D11: =VLOOKUP(C11,'Draft-Paysheet May 2026'!$C$4:$Q$51,15,0) -> #N/A | E11: =VLOOKUP(C11,'Draft-Paysheet May 2026'!$C$4:$AL$51,37,0) -> #N/A
A12: 9 | B12: 88V1007 | C12: Bhola Sharma | D12: =VLOOKUP(C12,'Draft-Paysheet May 2026'!$C$4:$Q$51,15,0) -> #N/A | E12: =VLOOKUP(C12,'Draft-Paysheet May 2026'!$C$4:$AL$51,37,0) -> #N/A
A13: 10 | B13: 88V1008 | C13: Sumant sharma | D13: =VLOOKUP(C13,'Draft-Paysheet May 2026'!$C$4:$Q$51,15,0) -> #N/A | E13: =VLOOKUP(C13,'Draft-Paysheet May 2026'!$C$4:$AL$51,37,0) -> #N/A
A14: 11 | B14: 88V1019 | C14: Deepinder Kumar Anand | D14: =VLOOKUP(C14,'Draft-Paysheet May 2026'!$C$4:$Q$51,15,0) -> #N/A | E14: =VLOOKUP(C14,'Draft-Paysheet May 2026'!$C$4:$AL$51,37,0) -> #N/A
A15: 12 | B15: 88V1029 | C15: Sandeep | D15: =VLOOKUP(C15,'Draft-Paysheet May 2026'!$C$4:$Q$51,15,0) -> 50100255004836 | E15: =VLOOKUP(C15,'Draft-Paysheet May 2026'!$C$4:$AL$51,37,0) -> #REF!
... A27: 24 | B27: 88V1114 | C27: Khushi Rupesh Subramanian | D27: =VLOOKUP(C27,'Draft-Paysheet May 2026'!$C$4:$Q$51,15,0) -> #N/A | E27: =VLOOKUP(C27,'Draft-Paysheet May 2026'!$C$4:$AL$51,37,0) -> #N/A
A28: 25 | B28: 88V1115 | C28: Unnati Singh | D28: =VLOOKUP(C28,'Draft-Paysheet May 2026'!$C$4:$Q$51,15,0) -> 50100810089015 | E28: =VLOOKUP(C28,'Draft-Paysheet May 2026'!$C$4:$AL$51,37,0) -> #REF! | K28: =20000 -> 20000
A29: 26 | B29: 88V1117 | C29: Krishan Pal Singh | D29: =VLOOKUP(C29,'Draft-Paysheet May 2026'!$C$4:$Q$51,15,0) -> #N/A | E29: =VLOOKUP(C29,'Draft-Paysheet May 2026'!$C$4:$AL$51,37,0) -> #N/A | K29: =K28/30*4 -> 2666.6667
A30: 27 | B30: 88V1120 | C30: Aayushi Pinakin Dhuvad | D30: =VLOOKUP(C30,'Draft-Paysheet May 2026'!$C$4:$Q$51,15,0) -> #N/A | E30: =VLOOKUP(C30,'Draft-Paysheet May 2026'!$C$4:$AL$51,37,0) -> #N/A | K30: =SUM(K28:K29) -> 22666.667
A31: 28 | C31: Sunil | E31: 22667
C33: Total | E33: =SUM(E4:E32) -> #REF!

Sheet Non HDFC for Bank
A1: Remitter_Account No. | B1: Remitter_Details | C1: Beneficiary_Name | D1: Amount | E1: IFSC Code | F1: Bank_Account_Number | G1: Beneficiary LEI Code
A2: 50200059258233 | B2: 88ACADEMICS INDIA PRIVATE LIMITED | C2: Narayan Kasat | D2: =VLOOKUP(C2,'Draft-Paysheet May 2026'!$C$4:$AL$51,37,0) -> #REF! | E2: =VLOOKUP(C2,'Draft-Paysheet May 2026'!$C$4:$R$51,16,0) -> UTIB0004626 | F2: =VLOOKUP(C2,'Draft-Paysheet May 2026'!$C$4:$R$51,15,0) -> 921010013386877
A3: 50200059258233 | B3: 88ACADEMICS INDIA PRIVATE LIMITED | C3: Babu Lal | D3: =VLOOKUP(C3,'Draft-Paysheet May 2026'!$C$4:$AL$51,37,0) -> #REF! | E3: =VLOOKUP(C3,'Draft-Paysheet May 2026'!$C$4:$R$51,16,0) -> UTIB0001007 | F3: =VLOOKUP(C3,'Draft-Paysheet May 2026'!$C$4:$R$51,15,0) -> 911010047193187
A4: 50200059258233 | B4: 88ACADEMICS INDIA PRIVATE LIMITED | C4: Gulshan | D4: =VLOOKUP(C4,'Draft-Paysheet May 2026'!$C$4:$AL$51,37,0) -> #REF! | E4: =VLOOKUP(C4,'Draft-Paysheet May 2026'!$C$4:$R$51,16,0) -> KVBL0004101 | F4: =VLOOKUP(C4,'Draft-Paysheet May 2026'!$C$4:$R$51,15,0) -> 4101155000110629
A5: 50200059258233 | B5: 88ACADEMICS INDIA PRIVATE LIMITED | C5: Rashi Gupta | D5: =VLOOKUP(C5,'Draft-Paysheet May 2026'!$C$4:$AL$51,37,0) -> #REF! | E5: =VLOOKUP(C5,'Draft-Paysheet May 2026'!$C$4:$R$51,16,0) -> SBIN0050324 | F5: =VLOOKUP(C5,'Draft-Paysheet May 2026'!$C$4:$R$51,15,0) -> 65122570810
A6: 50200059258233 | B6: 88ACADEMICS INDIA PRIVATE LIMITED | C6: Raj Kamal Sharma | D6: =VLOOKUP(C6,'Draft-Paysheet May 2026'!$C$4:$AL$51,37,0) -> #REF! | E6: =VLOOKUP(C6,'Draft-Paysheet May 2026'!$C$4:$R$51,16,0) -> SBIN0018166 | F6: =VLOOKUP(C6,'Draft-Paysheet May 2026'!$C$4:$R$51,15,0) -> 31582334723
A7: 50200059258233 | B7: 88ACADEMICS INDIA PRIVATE LIMITED | C7: Roshan Sharma | D7: =VLOOKUP(C7,'Draft-Paysheet May 2026'!$C$4:$AL$51,37,0) -> #REF! | E7: =VLOOKUP(C7,'Draft-Paysheet May 2026'!$C$4:$R$51,16,0) -> MAHB0001744 | F7: =VLOOKUP(C7,'Draft-Paysheet May 2026'!$C$4:$R$51,15,0) -> 60285501118
A8: 50200059258233 | B8: 88ACADEMICS INDIA PRIVATE LIMITED | C8: Mohan Kumar | D8: =VLOOKUP(C8,'Draft-Paysheet May 2026'!$C$4:$AL$51,37,0) -> #N/A | E8: =VLOOKUP(C8,'Draft-Paysheet May 2026'!$C$4:$R$51,16,0) -> #N/A | F8: =VLOOKUP(C8,'Draft-Paysheet May 2026'!$C$4:$R$51,15,0) -> #N/A
A9: 50200059258233 | B9: 88ACADEMICS INDIA PRIVATE LIMITED | C9: Meenakshi Gosai | D9: =VLOOKUP(C9,'Draft-Paysheet May 2026'!$C$4:$AL$51,37,0) -> #REF! | E9: =VLOOKUP(C9,'Draft-Paysheet May 2026'!$C$4:$R$51,16,0) -> IOBA0000766 | F9: =VLOOKUP(C9,'Draft-Paysheet May 2026'!$C$4:$R$51,15,0) -> 076601000061190
A10: 50200059258233 | B10: 88ACADEMICS INDIA PRIVATE LIMITED | C10: Deepa Chandnani | D10: ='Draft-Paysheet May 2026'!AL13 -> 42000 | E10: ='Draft-Paysheet May 2026'!R13 -> SBIN0032160 | F10: ='Draft-Paysheet May 2026'!Q13 -> 51116630705
A11: 50200059258233 | B11: 88ACADEMICS INDIA PRIVATE LIMITED | C11: Nidhi Gupta | D11: =VLOOKUP(C11,'Draft-Paysheet May 2026'!$C$4:$AL$51,37,0) -> #REF! | E11: =VLOOKUP(C11,'Draft-Paysheet May 2026'!$C$4:$R$51,16,0) -> CNRB0003160 | F11: =VLOOKUP(C11,'Draft-Paysheet May 2026'!$C$4:$R$51,15,0) -> 110037818923
A12: 50200059258233 | B12: 88ACADEMICS INDIA PRIVATE LIMITED | C12: Shalini Sharma | D12: =VLOOKUP(C12,'Draft-Paysheet May 2026'!$C$4:$AL$51,37,0) -> #REF! | E12: =VLOOKUP(C12,'Draft-Paysheet May 2026'!$C$4:$R$51,16,0) -> SBIN0011550 | F12: =VLOOKUP(C12,'Draft-Paysheet May 2026'!$C$4:$R$51,15,0) -> 20088263301
A13: 50200059258233 | B13: 88ACADEMICS INDIA PRIVATE LIMITED | C13: Vikas Panwar | D13: =VLOOKUP(C13,'Draft-Paysheet May 2026'!$C$4:$AL$51,37,0) -> #REF! | E13: =VLOOKUP(C13,'Draft-Paysheet May 2026'!$C$4:$R$51,16,0) -> KKBK0004596 | F13: =VLOOKUP(C13,'Draft-Paysheet May 2026'!$C$4:$R$51,15,0) -> 5246430031
A14: 50200059258233 | B14: 88ACADEMICS INDIA PRIVATE LIMITED | C14: Maheen Ajmali | D14: =VLOOKUP(C14,'Draft-Paysheet May 2026'!$C$4:$AL$51,37,0) -> #REF! | E14: =VLOOKUP(C14,'Draft-Paysheet May 2026'!$C$4:$R$51,16,0) -> SBIN0005918 | F14: =VLOOKUP(C14,'Draft-Paysheet May 2026'!$C$4:$R$51,15,0) -> 35853508559
A15: 50200059258233 | B15: 88ACADEMICS INDIA PRIVATE LIMITED | C15: Neelansh Pandey | D15: =VLOOKUP(C15,'Draft-Paysheet May 2026'!$C$4:$AL$51,37,0) -> #N/A | E15: =VLOOKUP(C15,'Draft-Paysheet May 2026'!$C$4:$R$51,16,0) -> #N/A | F15: =VLOOKUP(C15,'Draft-Paysheet May 2026'!$C$4:$R$51,15,0) -> #N/A
A16: 50200059258233 | B16: 88ACADEMICS INDIA PRIVATE LIMITED | C16: Arpit Acharya | D16: =VLOOKUP(C16,'Draft-Paysheet May 2026'!$C$4:$AL$51,37,0) -> #REF! | E16: =VLOOKUP(C16,'Draft-Paysheet May 2026'!$C$4:$R$51,16,0) -> HDFC0007285 | F16: =VLOOKUP(C16,'Draft-Paysheet May 2026'!$C$4:$R$51,15,0) -> 50100823730034
A17: 50200059258233 | B17: 88ACADEMICS INDIA PRIVATE LIMITED | C17: Sandeep Maurya | D17: =VLOOKUP(C17,'Draft-Paysheet May 2026'!$C$4:$AL$51,37,0) -> #REF! | E17: =VLOOKUP(C17,'Draft-Paysheet May 2026'!$C$4:$R$51,16,0) -> ICIC0000815 | F17: =VLOOKUP(C17,'Draft-Paysheet May 2026'!$C$4:$R$51,15,0) -> 051601003530
A18: 50200059258233 | B18: 88ACADEMICS INDIA PRIVATE LIMITED | C18: Priya Madan | D18: =VLOOKUP(C18,'Draft-Paysheet May 2026'!$C$4:$AL$51,37,0) -> #REF! | E18: =VLOOKUP(C18,'Draft-Paysheet May 2026'!$C$4:$R$51,16,0) -> UTIB0000739 | F18: =VLOOKUP(C18,'Draft-Paysheet May 2026'!$C$4:$R$51,15,0) -> 911010066143864
A19: 50200059258233 | B19: 88ACADEMICS INDIA PRIVATE LIMITED | C19: Monika Dhingra | D19: =VLOOKUP(C19,'Draft-Paysheet May 2026'!$C$4:$AL$51,37,0) -> #REF! | E19: =VLOOKUP(C19,'Draft-Paysheet May 2026'!$C$4:$R$51,16,0) -> ICIC0006301 | F19: =VLOOKUP(C19,'Draft-Paysheet May 2026'!$C$4:$R$51,15,0) -> 630101511988
A20: 50200059258233 | B20: 88ACADEMICS INDIA PRIVATE LIMITED | C20: Jyoti Singh | D20: =VLOOKUP(C20,'Draft-Paysheet May 2026'!$C$4:$AL$51,37,0) -> #REF! | E20: =VLOOKUP(C20,'Draft-Paysheet May 2026'!$C$4:$R$51,16,0) -> ICIC0007218 | F20: =VLOOKUP(C20,'Draft-Paysheet May 2026'!$C$4:$R$51,15,0) -> 721801500772
A21: 50200059258233 | B21: 88ACADEMICS INDIA PRIVATE LIMITED | C21: Sugandha Bhatnagar | D21: =VLOOKUP(C21,'Draft-Paysheet May 2026'!$C$4:$AL$51,37,0) -> #REF! | E21: =VLOOKUP(C21,'Draft-Paysheet May 2026'!$C$4:$R$51,16,0) -> IDIB000T553 | F21: =VLOOKUP(C21,'Draft-Paysheet May 2026'!$C$4:$R$51,15,0) -> 59084158508
A22: 50200059258233 | B22: 88ACADEMICS INDIA PRIVATE LIMITED | C22: Porikhit Das | D22: =VLOOKUP(C22,'Draft-Paysheet May 2026'!$C$4:$AL$51,37,0) -> #REF! | E22: =VLOOKUP(C22,'Draft-Paysheet May 2026'!$C$4:$R$51,16,0) -> KKBK0004575 | F22: =VLOOKUP(C22,'Draft-Paysheet May 2026'!$C$4:$R$51,15,0) -> 7546347903
... A42: 50200059258233 | B42: 88ACADEMICS INDIA PRIVATE LIMITED | C42: Aisha Sidhika | D42: =VLOOKUP(C42,'Draft-Paysheet May 2026'!$C$4:$AL$51,37,0) -> #REF! | E42: =VLOOKUP(C42,'Draft-Paysheet May 2026'!$C$4:$R$51,16,0) -> PUNB0491900 | F42: =VLOOKUP(C42,'Draft-Paysheet May 2026'!$C$4:$R$51,15,0) -> 4919000100044435
A43: 50200059258233 | B43: 88ACADEMICS INDIA PRIVATE LIMITED | C43: Riya | D43: =VLOOKUP(C43,'Draft-Paysheet May 2026'!$C$4:$AL$51,37,0) -> #REF! | E43: =VLOOKUP(C43,'Draft-Paysheet May 2026'!$C$4:$R$51,16,0) -> CNRB0019904 | F43: ='Draft-Paysheet May 2026'!Q51 -> 110043317026
C45: Total | D45: =SUM(D2:D44) -> #REF!

Sheet Leavers
A1: PAY_DATE | B1: Employee Code | C1: Employee Name | D1: Date of Join | E1: Gender | F1: Date of Birth | G1: Date of Leaving | H1: Father Name | I1: Department | J1: Designation | K1: Cost_Centre | L1: Work Location | M1: UAN_No | N1: PAN | O1: Aadhaar Number | P1: Bank Name | Q1: Account_No | R1: IFSC_Code | S1: Name As Per Bank | T1: Nationality | U1: Mobile Number | V1: Email ID | W1: STDDAYS | X1: LOP DAYS | Y1: WRKDAYS | Z1: Basic | AA1: Basic Arrear | AB1: House Rent Allowance | AC1: HRA Arrear | AD1: Special Allowance | AE1: LOP Reversals | AF1: Other Benefit | AG1: Total Salary | AH1: Salary Payable | AI1: TDS | AJ1: Monthly TDS | AK1: Provident Fund | AL1: PF Arrears | AM1: LWF | AN1: Net Salary Payable
A2: 30/11/2025 | B2: 88G1004 | C2: Simran Kumari Arora | D2: 01/11/2021 | E2: F | F2: 19/12/1996 | G2: 45930 | H2: Ramesh Arora | I2: Academic | J2: Asst. Manager | K2: NEW DELHI | L2: NEW DELHI | N2: DCXPA5508M | O2: 400878015992 | P2: HDFC BANK LTD | Q2: 50100367679688 | R2: HDFC0004754 | S2: Simran Arora | T2: INDIAN | U2: 7838783381 | V2: simranarora121996@gmail.com | W2: 31 | X2: 31 | Y2: =W2-X2 -> 0 | Z2: 23650 | AA2: 0 | AB2: 0 | AC2: 0 | AD2: 0 | AG2: =SUM(Z2:AD2) -> 23650 | AH2: =ROUND(AG2/W2*Y2,0) -> 0 | AK2: 0 | AL2: 0 | AM2: 0 | AN2: =AH2-SUM(AJ2:AM2) -> 0 | AQ2: 23650
A3: 30/11/2025 | B3: 88G1032 | C3: Kiran Pathak | D3: 06/04/2022 | E3: F | F3: 09/07/1996 | G3: 45930 | H3: Mr. Shiv Charan Pathak | I3: Academic | J3: Asst. Manager | K3: NEW DELHI | L3: NEW DELHI | N3: DHPPP5580M | O3: 441344227722 | P3: HDFC BANK LTD | Q3: 50100570445568 | R3: HDFC0004754 | S3: Kiran Pathak | T3: INDIAN | U3: 9911369360 | V3: pathakkiran233@gmail.com | W3: 31 | X3: 31 | Y3: =W3-X3 -> 0 | Z3: 23650 | AA3: 0 | AB3: 0 | AC3: 0 | AD3: 0 | AG3: =SUM(Z3:AD3) -> 23650 | AH3: =ROUND(AG3/W3*Y3,0) -> 0 | AK3: 0 | AL3: 0 | AM3: 0 | AN3: =AH3-SUM(AJ3:AM3) -> 0 | AQ3: 23650
A4: 30/11/2025 | B4: 88G1076 | C4: Neelansh Pandey | D4: 27/03/2023 | E4: M | F4: 29/12/1999 | G4: 45930 | H4: Maneesh Pandey | I4: Technology | J4: Software Engineer | K4: NEW DELHI | L4: NEW DELHI | N4: GBWPP6646A | O4: 725384430510 | P4: FEDERAL BANK | Q4: 55550125053999 | R4: FDRL0005555 | S4: Neelansh Pandey | T4: INDIAN | U4: 9696472351 | V4: neelansh.email@gmail.com | W4: 31 | X4: 31 | Y4: =W4-X4 -> 0 | Z4: 21000 | AA4: 0 | AB4: 6500 | AC4: 0 | AD4: 0 | AG4: =SUM(Z4:AD4) -> 27500 | AH4: =ROUND(AG4/W4*Y4,0) -> 0 | AK4: 0 | AL4: 0 | AM4: 0 | AN4: =AH4-SUM(AJ4:AM4) -> 0
A5: 30/11/2025 | B5: 88V1006 | C5: Shalu Gandhi | D5: 01/11/2021 | E5: F | F5: 02/04/1994 | G5: 45946 | H5: Mr. Manoj Kumar | I5: VGLD | J5: Business Development Manager | K5: NEW DELHI | L5: NEW DELHI | N5: FTEPS2950H | O5: 521413766561 | P5: HDFC BANK LTD | Q5: 50100320374664 | R5: HDFC0004400 | S5: Shalu Gandhi | T5: INDIAN | U5: 8178558699 | V5: Princessshalu41@gmail.com | W5: 31 | X5: =(16-0.4) -> 15.6 | Y5: =W5-X5 -> 15.4 | Z5: 21000 | AA5: 0 | AB5: 9500 | AC5: 0 | AD5: 9500 | AG5: =SUM(Z5:AD5) -> 40000 | AH5: =ROUND(AG5/W5*Y5,0) -> 19871 | AK5: 0 | AL5: 0 | AM5: 0 | AN5: =AH5-SUM(AJ5:AM5) -> 19871
A6: 30/11/2025 | B6: 88V1007 | C6: Bhola Sharma | D6: 01/11/2021 | E6: M | F6: 21/03/1990 | G6: 45930 | H6: Ram Briksh Sharma | I6: IT | J6: Team Lead | K6: NEW DELHI | L6: NEW DELHI | N6: EMTPS5809G | O6: 358945706233 | P6: HDFC BANK LTD | Q6: 50100671464827 | R6: HDFC0002509 | S6: Bhola Sharma | T6: INDIAN | U6: 8010418160 | V6: bhola334@gmail.com | W6: 31 | X6: 31 | Y6: =W6-X6 -> 0 | Z6: 32100 | AA6: 0 | AB6: 16050 | AC6: 0 | AD6: 16050 | AG6: =SUM(Z6:AD6) -> 64200 | AH6: =ROUND(AG6/W6*Y6,0) -> 0 | AK6: 0 | AL6: 0 | AM6: 0 | AN6: =AH6-SUM(AJ6:AM6) -> 0
A7: 30/11/2025 | B7: 88V1008 | C7: Sumant sharma | D7: 01/11/2021 | E7: M | F7: 26/06/1997 | G7: 45930 | H7: Mr. Dayanand Sharma | I7: IT | J7: Jr. Software Engineer | K7: NEW DELHI | L7: NEW DELHI | N7: MBWPS9718L | O7: 436349720443 | P7: HDFC BANK LTD | Q7: 50100471094691 | R7: HDFC0002509 | S7: Sumant sharma | T7: INDIAN | U7: 8115019830 | V7: sharmasumant092@gmail.com | W7: 31 | X7: 31 | Y7: =W7-X7 -> 0 | Z7: 25000 | AA7: 0 | AB7: 0 | AC7: 0 | AD7: 0 | AG7: =SUM(Z7:AD7) -> 25000 | AH7: =ROUND(AG7/W7*Y7,0) -> 0 | AK7: 0 | AL7: 0 | AM7: 0 | AN7: =AH7-SUM(AJ7:AM7) -> 0
A8: 30/11/2025 | B8: 88V1019 | C8: Deepinder Kumar Anand | D8: 01/08/2022 | E8: M | F8: 19/08/1989 | G8: 45930 | H8: Gyan Chand | I8: VGLD | J8: Manager | K8: NEW DELHI | L8: NEW DELHI | N8: BJSPA7312P | O8: 866993461179 | P8: HDFC BANK LTD | Q8: 50100374469868 | R8: HDFC0004754 | S8: Deepinder Kumar Anand | T8: INDIAN | U8: 8527697920 | V8: deependeranand89@gmail.com | W8: 31 | X8: 31 | Y8: =W8-X8 -> 0 | Z8: 30250 | AA8: 0 | AB8: 15125 | AC8: 0 | AD8: 15125 | AG8: =SUM(Z8:AD8) -> 60500 | AH8: =ROUND(AG8/W8*Y8,0) -> 0 | AK8: 0 | AL8: 0 | AM8: 0 | AN8: =AH8-SUM(AJ8:AM8) -> 0
A9: 30/11/2025 | B9: 88V1074 | C9: Shailja Dhyani | D9: 18/03/2024 | E9: F | F9: 15/09/1980 | G9: 45930 | H9: Gangaram Bhardwaj | I9: Technology | J9: Software Engineer | K9: NEW DELHI | L9: NEW DELHI | N9: ASLPD0880A | O9: 952955251762 | P9: STATE BANK OF INDIA | Q9: 30838184866 | R9: SBIN0032182 | S9: Shailja Dhyani | T9: Indian | U9: 9205031014 | V9: dhyani.shailja@gmail.com | W9: 31 | X9: 31 | Y9: =W9-X9 -> 0 | Z9: 21000 | AA9: 0 | AB9: 7000 | AC9: 0 | AD9: 0 | AG9: =SUM(Z9:AD9) -> 28000 | AH9: =ROUND(AG9/W9*Y9,0) -> 0 | AK9: 0 | AL9: 0 | AM9: 0 | AN9: =AH9-SUM(AJ9:AM9) -> 0
A10: 30/11/2025 | B10: 88V1082 | C10: Neha Dhall | D10: 24/04/2024 | E10: F | F10: 12/07/2000 | G10: 45958 | H10: Parveen Dhall | I10: VGLD | J10: Business Development Manager | K10: NEW DELHI | L10: NEW DELHI | N10: EZLPD7666B | O10: 607133965459 | P10: UNION BANK OF INDIA | Q10: 639502010012535 | R10: UBIN0563951 | S10: Neha Dhall | T10: Indian | U10: 9711826778 | V10: dhallneha2000@gmail.com | W10: 31 | X10: 5.5 | Y10: =W10-X10 -> 25.5 | Z10: 21000 | AA10: 0 | AB10: 4300 | AC10: 0 | AD10: 0 | AG10: =SUM(Z10:AD10) -> 25300 | AH10: =ROUND(AG10/W10*Y10,0) -> 20811 | AK10: 0 | AL10: 0 | AM10: 0 | AN10: =AH10-SUM(AJ10:AM10) -> 20811
A11: 30/11/2025 | B11: 88V1084 | C11: Ankita Rajput | D11: 08/05/2024 | E11: F | F11: 02/05/2001 | G11: 45930 | H11: suresh chandra | I11: VGLD | J11: Business Development Manager | K11: NEW DELHI | L11: NEW DELHI | N11: EFGPR7171A | O11: 417687447753 | P11: STATE BANK OF INDIA | Q11: 38532821158 | R11: SBIN0061203 | S11: Ankita Rajput | T11: Indian | U11: 9315039537 | V11: iamankitarajput3@gmail.com | W11: 31 | X11: 31 | Y11: =W11-X11 -> 0 | Z11: 25000 | AA11: 0 | AB11: 0 | AC11: 0 | AD11: 0 | AG11: =SUM(Z11:AD11) -> 25000 | AH11: =ROUND(AG11/W11*Y11,0) -> 0 | AK11: 0 | AL11: 0 | AM11: 0 | AN11: =AH11-SUM(AJ11:AM11) -> 0 | AR11: 25000
A12: 31-12-2025 | B12: 88G1074 | C12: Rakesh Singh Rawat | D12: 14/03/2023 | E12: M | F12: 03/05/1976 | G12: 45972 | H12: Balwant Singh Rawat | I12: Academic | J12: Asst. Manager | K12: NEW DELHI | L12: NEW DELHI | N12: BUYPR5567C | O12: 621229408319 | P12: HDFC BANK LTD | Q12: 50100605279393 | R12: HDFC0003687 | S12: Rakesh Singh Rawat | T12: INDIAN | U12: 9013600858 | V12: rsrawatdtp9@gmail.com | W12: 31 | X12: 0 | Y12: =W12-X12 -> 31 | Z12: 21000 | AA12: 0 | AB12: 3200 | AC12: 0 | AD12: 0 | AE12: =SUM(Z12:AD12) -> 24200 | AF12: =ROUND(AE12/W12*Y12,0) -> 24200 | AJ12: 0 | AK12: 0 | AL12: 0 | AM12: =AF12-SUM(AI12:AL12) -> 24200
A13: 31-12-2025 | B13: 88V1054 | C13: Dharna Jain | D13: 04/12/2023 | E13: F | F13: 07/01/2000 | G13: 45880 | H13: Rajesh Jain | I13: VGLD | J13: Business Development Manager | K13: NEW DELHI | L13: NEW DELHI | N13: BVXPJ3487P | O13: 607361874982 | P13: HDFC BANK LTD | Q13: 50100618103035 | R13: HDFC0002091 | S13: Dharna Jain | T13: INDIAN | U13: 954018168 | V13: dharnajain07@gmail.com | W13: 31 | X13: 0 | Y13: =W13-X13 -> 31 | Z13: 21175 | AA13: 0 | AB13: 10588 | AC13: 0 | AD13: 10588 | AE13: =SUM(Z13:AD13) -> 42351 | AF13: =ROUND(AE13/W13*Y13,0) -> 42351 | AJ13: 0 | AK13: 0 | AL13: 0 | AM13: =AF13-SUM(AI13:AL13) -> 42351
A14: 31-12-2025 | B14: 88V1094 | C14: CH Shiva | D14: 08/07/2024 | E14: M | F14: 22/02/1995 | G14: 45850 | H14: Ch Viswanath | I14: VGLD | J14: Business Development Manager | K14: NEW DELHI | L14: NEW DELHI | N14: LZXPS7724L | O14: 708102547472 | P14: BANK OF BARODA | Q14: 05120100031898 | R14: BARB0SECUND | S14: CH Shiva | T14: Indian | U14: 9348489443 | V14: chshiva3877@gmail.com | W14: 31 | X14: 25 | Y14: =W14-X14 -> 6 | Z14: 21000 | AA14: 0 | AB14: 9500 | AC14: 0 | AD14: 9500 | AE14: =SUM(Z14:AD14) -> 40000 | AF14: =ROUND(AE14/W14*Y14,0) -> 7742 | AG14: 1500 | AJ14: 0 | AK14: 0 | AL14: 0 | AM14: =AF14-SUM(AI14:AL14)+AG14 -> 9242
A15: 31-12-2025 | B15: 88V1117 | C15: Krishan Pal Singh | D15: 01/07/2025 | E15: M | F15: 30/06/2000 | G15: 15-12-2025 | H15: Dileep Singh | I15: Academic | J15: Business Development Manager | K15: NEW DELHI | L15: NEW DELHI | N15: LNMPS6237H | O15: 988998640555 | P15: HDFC BANK LTD | Q15: 50100539685358 | R15: HDFC0002670 | S15: Krishan Pal Singh | T15: Indian | U15: 9602349484 | V15: kpbanna.singh05@gmail.com | W15: 31 | X15: 17 | Y15: =W15-X15 -> 14 | Z15: 21000 | AA15: 0 | AB15: 9000 | AC15: 0 | AD15: 9000 | AE15: =SUM(Z15:AD15) -> 39000 | AF15: =ROUND(AE15/W15*Y15,0) -> 17613 | AJ15: 0 | AK15: 0 | AL15: 0 | AM15: =AF15-SUM(AI15:AL15) -> 17613
A16: 31-01-2026 | B16: 88V1056 | C16: Arvind Kumar Mahto | D16: 06/12/2023 | E16: M | F16: 11/12/1993 | G16: 46023 | H16: Lalman Mahto | I16: VGLD | J16: Senior Business Development Manager | K16: NEW DELHI | L16: NEW DELHI | N16: DSMPM3816B | O16: 696062126697 | P16: IDFC FIRST BANK LTD | Q16: 10149719238 | R16: IDFB0020217 | S16: Arvind Kumar Mahto | T16: INDIAN | U16: 7481033282 | V16: iamarvinkr@gmail.com | W16: 31 | X16: 0 | Y16: =W16-X16 -> 31 | Z16: 23100 | AA16: 0 | AB16: 11000 | AC16: 0 | AD16: 11000 | AE16: =SUM(Z16:AD16) -> 45100 | AF16: =ROUND(AE16/W16*Y16,0) -> 45100 | AJ16: 0 | AK16: 0 | AL16: 0 | AM16: =AF16-SUM(AI16:AL16) -> 45100
A17: 31-01-2026 | B17: 88V1114 | C17: Khushi Rupesh Subramanian | D17: 21/04/2025 | E17: F | F17: 12/02/2002 | G17: 46023 | H17: Rupesh | I17: VGLD | J17: Sr. Business Development Executive | K17: NEW DELHI | L17: NEW DELHI | N17: NMZPS9682A | O17: 299601769647 | P17: HDFC BANK LTD | Q17: 50100496616101 | R17: HDFC0000411 | S17: Khushi Rupesh Subramanian | T17: Indian | U17: 7738321038 | V17: subramaniankhushi@gmail.com | W17: 31 | X17: 0 | Y17: =W17-X17 -> 31 | Z17: 21000 | AA17: 0 | AB17: 9500 | AC17: 0 | AD17: 9500 | AE17: =SUM(Z17:AD17) -> 40000 | AF17: =ROUND(AE17/W17*Y17,0) -> 40000 | AJ17: 0 | AK17: 0 | AL17: 0 | AM17: =AF17-SUM(AI17:AL17) -> 40000
A18: 31-01-2026 | B18: 88V1120 | C18: Aayushi Pinakin Dhuvad | D18: 15-09-2025 | E18: F | F18: 37714 | G18: 46023 | J18: Sr. Business Development Executive | K18: Mumbai | L18: Mumbai | P18: HDFC BANK LTD | Q18: 50100661851456 | R18: HDFC0000542 | S18: AAYUSHI PINAKIN DHUVAD | T18: Indian | W18: 31 | X18: 0 | Y18: =W18-X18 -> 31 | Z18: 22500 | AB18: 11250 | AC18: 0 | AD18: 11250 | AE18: =SUM(Z18:AD18) -> 45000 | AF18: =ROUND(AE18/W18*Y18,0) -> 45000 | AH18: 0 | AI18: 0 | AJ18: 0 | AK18: 0 | AL18: 0 | AM18: =AF18-SUM(AI18:AL18) -> 45000
A19: 31-01-2026 | B19: 88V1075 | C19: Nishant Goswami | D19: 01/04/2024 | E19: M | F19: 12/01/1991 | G19: 46023 | H19: VIMAL GOSWAMI | I19: VGLD | J19: Senior Business Development Manager | K19: NEW DELHI | L19: NEW DELHI | N19: BMYPG9702L | O19: 615260204495 | P19: AXIS BANK | Q19: 918010009771050 | R19: UTIB0000268 | S19: Nishant Goswami | T19: Indian | U19: 9717032182 | V19: nishant.goswami551@gmail.com | W19: 31 | X19: 0 | Y19: =W19-X19 -> 31 | Z19: 23650 | AA19: 0 | AB19: 11825 | AC19: 0 | AD19: 11825 | AE19: =SUM(Z19:AD19) -> 47300 | AF19: =ROUND(AE19/W19*Y19,0) -> 47300 | AJ19: 0 | AK19: 0 | AL19: 0 | AM19: =AF19-SUM(AI19:AL19) -> 47300
A20: 31-05-2026 | B20: 88G1008 | C20: Mohan Kumar | D20: 01/11/2021 | E20: M | F20: 13/12/1990 | H20: Mr. Arun Kumar Sahu | I20: IT | J20: Team Lead | K20: NEW DELHI | L20: NEW DELHI | N20: DDCPK9632Q | O20: 669511376061 | P20: UNION BANK OF INDIA | Q20: 520101231465821 | R20: UBIN0911691 | S20: Mohan Kumar | T20: INDIAN | U20: 9540409376 | V20: mohankr2006@gmail.com | W20: 31 | Y20: =W20-X20 -> 31 | Z20: 51900 | AA20: 0 | AB20: 25950 | AC20: 0 | AD20: 25950 | AE20: =SUM(Z20:AD20) -> 103800 | AF20: =ROUND(AE20/W20*Y20,0) -> 103800 | AG20: 0 | AI20: 0 | AJ20: 0 | AK20: 0 | AL20: =AF20-SUM(AH20:AK20)+AG20 -> 103800
A21: 31-05-2026 | B21: 88V1057 | C21: Aman Singh | D21: 06/12/2023 | E21: M | F21: 11/07/1992 | G21: 30-04-2026 | H21: Rajesh pratap singh | I21: VGLD | J21: Senior Business Development Manager | K21: NEW DELHI | L21: NEW DELHI | N21: EPGPS2324Q | O21: 479838863151 | P21: HDFC BANK LTD | Q21: 50100215227754 | R21: HDFC0001203 | S21: Aman Singh | T21: INDIAN | U21: 9958392183 | V21: aman.singh52820@gmail.com | W21: 31 | Y21: =W21-X21 -> 31 | Z21: 24750 | AA21: 0 | AB21: 12375 | AC21: 0 | AD21: 12375 | AE21: =SUM(Z21:AD21) -> 49500 | AF21: =ROUND(AE21/W21*Y21,0) -> 49500 | AI21: 0 | AJ21: 0 | AK21: 0 | AL21: =AF21-SUM(AH21:AK21) -> 49500
A22: 31-05-2026 | B22: 88V1092 | C22: Rajesh Machhiya | D22: 10/06/2024 | E22: M | F22: 04/03/1992 | G22: 46299 | H22: L P Machhiya | I22: VGLD | J22: Business Development Manager | K22: NEW DELHI | L22: NEW DELHI | N22: CBXPR5100G | O22: 309570572311 | P22: CENTRAL BANK OF INDIA | Q22: 5574729862 | R22: CBIN0280111 | S22: Rajesh Machhiya | T22: Indian | U22: 9179727057 | V22: machhiyarajesh38@gmail.com | W22: 31 | Y22: =W22-X22 -> 31 | Z22: =22000 -> 22000 | AA22: 0 | AB22: 4500 | AC22: 0 | AD22: 3500 | AE22: =SUM(Z22:AD22) -> 30000 | AF22: =ROUND(AE22/W22*Y22,0) -> 30000 | AI22: 0 | AJ22: 0 | AK22: 0 | AL22: =AF22-SUM(AH22:AK22) -> 30000
A23: 31-05-2026 | B23: 88V1078 | C23: Ishant Garg | D23: 08/04/2024 | E23: M | F23: 02/10/2004 | H23: Anil Garg | I23: VGLD | J23: Business Development Manager | K23: NEW DELHI | L23: NEW DELHI | N23: EAPPG4081N | O23: 336156425108 | P23: HDFC BANK LTD | Q23: 99990027081982 | R23: HDFC0004782 | S23: Ishant Garg | T23: Indian | U23: 8178702039 | V23: ishantgarg9899@gmail.com | W23: 31 | Y23: =W23-X23 -> 31 | Z23: 23100 | AA23: 0 | AB23: 10780 | AC23: 0 | AD23: 0 | AE23: =SUM(Z23:AD23) -> 33880 | AF23: =ROUND(AE23/W23*Y23,0) -> 33880 | AG23: 0 | AI23: 0 | AJ23: 0 | AK23: 0 | AL23: =AF23-SUM(AH23:AK23)+AG23 -> 33880

Sheet Mumbai

Sheet Chennai
A1: Date | B1: SAGAR | C1: RIYA | D1: AISHA | E1: DEEP (Counsellor)
A2: 46143 | B2: Present | C2: Present | D2: Present | E2: Present
A3: 46144 | B3: Present | C3: Present | D3: Present | E3: Present
A4: 46145 | B4: SUNDAY
A5: 46146 | B5: Present | C5: Present | D5: Present | E5: Present
A6: 46147 | B6: Present | C6: Present | D6: Present | E6: Present
A7: 46148 | B7: Present | C7: Present | D7: Present | E7: Present
A8: 46149 | B8: Present | C8: Present | D8: Present | E8: Present
A9: 46150 | B9: Present | C9: Present | D9: Present | E9: Present
A10: 46151 | B10: Present | C10: Present | D10: Present | E10: Present
A11: 46152 | B11: SUNDAY
A12: 46153 | B12: Present | C12: Present | D12: Present | E12: Present
A13: 46154 | B13: Present | C13: Present | D13: Present | E13: Half a day Leave
A14: 46155 | B14: Present | C14: Present | D14: Present | E14: Present
A15: 46156 | B15: Present | C15: Present | D15: Present | E15: Present
A16: 46157 | B16: Present | C16: Present | D16: Present | E16: Present
A17: 46158 | B17: Present | C17: Present | D17: Present | E17: Present
A18: 46159 | B18: SUNDAY
A19: 46160 | B19: Present | C19: Present | D19: Present | E19: Present
A20: 46161 | B20: Present | C20: Present | D20: Present | E20: Present
A21: 46162 | B21: Present | C21: Present | D21: Present | E21: Present
A22: 46163 | B22: Present | C22: Present | D22: Present | E22: Present
A23: 46164 | B23: Present | C23: Present | D23: Present | E23: Present
A24: 46165 | B24: Present | C24: Present | D24: Present | E24: Present
A25: 46166 | B25: SUNDAY
A26: 46167 | B26: Present | C26: Present | D26: Present | E26: Present
A27: 46168 | B27: Present | C27: Present | D27: Present | E27: Present
A28: 46169 | B28: Present | C28: Present | D28: Present | E28: Present
A29: 46170 | B29: Present | C29: Leave | D29: Leave | E29: Present
A30: 46171 | B30: Present | C30: Present | D30: Present | E30: Present
A31: 46172 | B31: Present | C31: Present | D31: Present | E31: Present
A32: 46173 | B32: SUNDAY

Sheet TDS
C2: Month | D2: Narayan Kasat | E2: Babu Lal | F2: Anita Dubey | G2: Mohan Kumar
C3: April | D3: 300000 | E3: 191241 | F3: =H31 -> 168162 | G3: 103800
C4: May | D4: 300000 | E4: 191241 | F4: =H32 -> 102018 | G4: 103800
C5: June | D5: 300000 | E5: 191241 | F5: =H33 -> 108333 | G5: 103800
C6: July | D6: 300000 | E6: 191241 | F6: =H34 -> 108333 | G6: 103800
C7: August | D7: 300000 | E7: 191241 | F7: =H35 -> 108333 | G7: 103800
C8: September | D8: 300000 | E8: 191241 | F8: =H36 -> 108333 | G8: 103800
C9: October | D9: 300000 | E9: 191241 | F9: =H37 -> 108333 | G9: 103800
C10: November | D10: 300000 | E10: 191241 | F10: =H38 -> 108333 | G10: 103800
C11: December | D11: 300000 | E11: 191241 | F11: =H39 -> 108333 | G11: 103800
C12: January | D12: 300000 | E12: 191241 | F12: =H40 -> 108333 | G12: 103800
C13: February | D13: 300000 | E13: 191241 | F13: =H41 -> 108333 | G13: 103800
C14: March | D14: 300000 | E14: 191241 | F14: =H42 -> 108333 | G14: 103800
C16: Total Salary | D16: =SUM(D3:D14) -> 3600000 | E16: =SUM(E3:E14) -> 2294892 | F16: =SUM(F3:F14) -> 1353510 | G16: =SUM(G3:G14) -> 1245600
C17: Less: Standard Deduction | D17: 75000 | E17: 75000 | F17: 75000 | G17: 75000
C19: Net Taxable Salary | D19: =D16-D17 -> 3525000 | E19: =E16-E17 -> 2219892 | F19: =F16-F17 -> 1278510 | G19: =G16-G17 -> 1170600
C20: Tax
C21: Gross Tax | D21: 663000 | E21: 256168 | F21: 66298 | G21: 0
C22: Add: Cess 3% | D22: =D21*0.03 -> 19890 | E22: =E21*0.03 -> 7685.04 | F22: =F21*0.03 -> 1988.94 | G22: =G21*0.03 -> 0
C24: Net Tax Liability | D24: =SUM(D21:D23) -> 682890 | E24: =SUM(E21:E23) -> 263853.04 | F24: =SUM(F21:F23) -> 68286.94 | G24: =SUM(G21:G23) -> 0
C25: Monthly TDS | D25: =D24/12 -> 56907.5 | E25: =E24/12 -> 21987.753 | F25: =F24/12 -> 5690.5783 | G25: =G24/12 -> 0
C30: Month | D30: Salary | E30: Incentive | F30: Total Salary | G30: TDS | H30: Total
C31: April | D31: 108333 | E31: 65520 | F31: =D31+E31 -> 173853 | G31: 5691 | H31: =F31-G31 -> 168162
C32: May | D32: 108333 | F32: =D32+E32 -> 108333 | G32: 6315 | H32: =F32-G32 -> 102018
C33: June | D33: 108333 | F33: =D33+E33 -> 108333 | H33: =F33-G33 -> 108333
C34: July | D34: 108333 | F34: =D34+E34 -> 108333 | H34: =F34-G34 -> 108333
C35: August | D35: 108333 | F35: =D35+E35 -> 108333 | H35: =F35-G35 -> 108333
C36: September | D36: 108333 | F36: =D36+E36 -> 108333 | H36: =F36-G36 -> 108333
C37: October | D37: 108333 | F37: =D37+E37 -> 108333 | H37: =F37-G37 -> 108333
C38: November | D38: 108333 | F38: =D38+E38 -> 108333 | H38: =F38-G38 -> 108333
C39: December | D39: 108333 | F39: =D39+E39 -> 108333 | H39: =F39-G39 -> 108333
C40: January | D40: 108333 | F40: =D40+E40 -> 108333 | H40: =F40-G40 -> 108333
C41: February | D41: 108333 | F41: =D41+E41 -> 108333 | H41: =F41-G41 -> 108333
C42: March | D42: 108333 | F42: =D42+E42 -> 108333 | H42: =F42-G42 -> 108333
H43: =F43-G43 -> 0
C44: Total | F44: =SUM(F31:F43) -> 1365516
C45: Less; Standard Deduction | F45: 75000
C47: Net Taxable Salary | F47: =F44-F45 -> 1290516
C48: Gross Tax Liability | F48: =IF(F47<=400000,0, IF(F47<=800000,(F47-400000)*5%, IF(F47<=1200000,(400000*5%)+(F47-800000)*10%, IF(F47<=1600000,(400000*5%)+(400000*10%)+(F47-1200000)*15%, IF(F47<=2000000,(400000*5%)+(400000*10%)+(400000*15%)+(E24-1600000)*20%, IF(F47<=2400000,(400000*5%)+(400000*10%)+(400000*15%)+(400000*20%)+(F47-2000000)*25%, (400000*5%)+(400000*10%)+(400000*15%)+(400000*20%)+(400000*25%)+(F47-2400000)*30%)))))) -> 73577.4
C49: Add: Cess 3% | F49: =F48*0.03 -> 2207.322
C50: Net Tax LIability | F50: =F48+F49 -> 75784.722
C52: Monthly TDS | F52: =F50/12 -> 6315.3935

Sheet LKO
A1: 88academics Pvt Ltd Employee's Performance Register For the Month of : May-2026
A2: Place Name:
A3: Date | D3: 1 | E3: 2 | F3: 3 | G3: 4 | H3: 5 | I3: 6 | J3: 7 | K3: 8 | L3: 9 | M3: 10 | N3: 11 | O3: 12 | P3: 13 | Q3: 14 | R3: 15 | S3: 16 | T3: 17 | U3: 18 | V3: 19 | W3: 20 | X3: 21 | Y3: 22 | Z3: 23 | AA3: 24 | AB3: 25 | AC3: 26 | AD3: 27 | AE3: 28 | AF3: 29 | AG3: 30 | AH3: 31 | AI3: Present | AJ3: Absent | AK3: Leave | AL3: Remarks
A4: Sr. No | B4: Employee Code | C4: Employee Name | AI4: =COUNTIF(D4:AH4,"P") -> 0 | AJ4: =COUNTIF(D4:AH4,"A") -> 0 | AK4: =COUNTIF(D4:AH4,"L") -> 0
A5: 6 | C5: Ravi Dubey (Lucknow) | D5: P | E5: P | F5: WO | G5: P | H5: P | I5: P | J5: P | K5: P | L5: P | M5: WO | N5: P | O5: SL | P5: P | Q5: P | R5: P | S5: P | T5: WO | U5: P | V5: P | W5: P | X5: P | Y5: P | Z5: P | AA5: WO | AB5: P | AC5: P | AD5: P | AE5: P | AF5: P | AG5: P | AH5: WO | AI5: =COUNTIF(D5:AH5,"P") -> 25 | AJ5: =COUNTIF(D5:AH5,"A") -> 0 | AK5: =COUNTIF(D5:AH5,"L") -> 0
A6: 7 | AI6: =COUNTIF(D6:AH6,"P") -> 0 | AJ6: =COUNTIF(D6:AH6,"A") -> 0 | AK6: =COUNTIF(D6:AH6,"L") -> 0
A7: 11 | AI7: =COUNTIF(D7:AH7,"P") -> 0 | AJ7: =COUNTIF(D7:AH7,"A") -> 0 | AK7: =COUNTIF(D7:AH7,"L") -> 0
A8: 12 | AI8: =COUNTIF(D8:AH8,"P") -> 0 | AJ8: =COUNTIF(D8:AH8,"A") -> 0 | AK8: =COUNTIF(D8:AH8,"L") -> 0
A9: 13 | AI9: =COUNTIF(D9:AH9,"P") -> 0 | AJ9: =COUNTIF(D9:AH9,"A") -> 0 | AK9: =COUNTIF(D9:AH9,"L") -> 0
A10: 14 | AI10: =COUNTIF(D10:AH10,"P") -> 0 | AJ10: =COUNTIF(D10:AH10,"A") -> 0 | AK10: =COUNTIF(D10:AH10,"L") -> 0
A11: 15 | AI11: =COUNTIF(D11:AH11,"P") -> 0 | AJ11: =COUNTIF(D11:AH11,"A") -> 0 | AK11: =COUNTIF(D11:AH11,"L") -> 0
A12: 16 | AI12: =COUNTIF(D12:AH12,"P") -> 0 | AJ12: =COUNTIF(D12:AH12,"A") -> 0 | AK12: =COUNTIF(D12:AH12,"L") -> 0
A13: 17 | AI13: =COUNTIF(D13:AH13,"P") -> 0 | AJ13: =COUNTIF(D13:AH13,"A") -> 0 | AK13: =COUNTIF(D13:AH13,"L") -> 0
A14: 18 | AI14: =COUNTIF(D14:AH14,"P") -> 0 | AJ14: =COUNTIF(D14:AH14,"A") -> 0 | AK14: =COUNTIF(D14:AH14,"L") -> 0
A15: 19 | AI15: =COUNTIF(D15:AH15,"P") -> 0 | AJ15: =COUNTIF(D15:AH15,"A") -> 0 | AK15: =COUNTIF(D15:AH15,"L") -> 0
A16: 20 | AI16: =COUNTIF(D16:AH16,"P") -> 0 | AJ16: =COUNTIF(D16:AH16,"A") -> 0 | AK16: =COUNTIF(D16:AH16,"L") -> 0
A17: 21 | AI17: =COUNTIF(D17:AH17,"P") -> 0 | AJ17: =COUNTIF(D17:AH17,"A") -> 0 | AK17: =COUNTIF(D17:AH17,"L") -> 0
... A35: 39 | AI35: =COUNTIF(D35:AH35,"P") -> 0 | AJ35: =COUNTIF(D35:AH35,"A") -> 0 | AK35: =COUNTIF(D35:AH35,"L") -> 0

Sheet Hyd
A2: Date | D2: 1 | E2: 2 | F2: 3 | G2: 4 | H2: 5 | I2: 6 | J2: 7 | K2: 8 | L2: 9 | M2: 10 | N2: 11 | O2: 12 | P2: 13 | Q2: 14 | R2: 15 | S2: 16 | T2: 17 | U2: 18 | V2: 19 | W2: 20 | X2: 21 | Y2: 22 | Z2: 23 | AA2: 24 | AB2: 25 | AC2: 26 | AD2: 27 | AE2: 28 | AF2: 29 | AG2: 30 | AH2: Present | AI2: Absent | AJ2: Leave | AK2: Remarks
A3: Sr. No | B3: Employee Code | C3: Employee Name | AH3: 0 | AI3: 0 | AJ3: 0
A4: 1 | B4: 88V1052 | C4: Anita Dubay
A5: 2 | B5: 88V1067 | C5: Sangeeta Chourasia

Sheet Sheet1
C5: Income Anita Dubey
C7: April | D7: May | E7: June | F7: July | G7: August | H7: September | I7: October | J7: November | K7: Dec | L7: Jan | M7: Feb | N7: Mar | O7: Total
B8: Salary | C8: 108333 | D8: 108333 | E8: 108333 | F8: 108333 | G8: =108333 -> 108333 | H8: =F8 -> 108333 | I8: 108333 | J8: =H8 -> 108333 | K8: =I8 -> 108333 | L8: =J8 -> 108333 | M8: =K8 -> 108333 | N8: =L8 -> 108333 | O8: =SUM(C8:N8) -> 1299996 | P8: 26000
B9: Incentive | G9: 17680 | O9: =SUM(C9:N9) -> 17680 | P9: 44380
B10: TDS | C10: =26000/12 -> 2166.6667 | D10: =26000/12 -> 2166.6667 | E10: =26000/12 -> 2166.6667 | F10: =26000/12 -> 2166.6667 | G10: =(44380-SUM(C10:F10))/8 -> 4464.1667 | H10: 4464 | I10: 4464 | J10: 4464 | K10: 4464 | L10: 4464 | M10: 4464 | N10: 4464 | O10: =SUM(C10:N10) -> 44378.833
AA18: Basic Salary
B19: 45930 | C19: 88V1121 | D19: Riya | E19: 45925 | F19: F | G19: 36123 | I19: Jasinta Tirkey | K19: Business Development Executive | L19: Chennai | M19: Chennai | O19: FNDPR1926P | P19: 932282568271 | Q19: Canera Bank | R19: 110043317026 | S19: CNRB0019904 | T19: Riya | U19: Indian | V19: 9289909280 | W19: Riyachh143@gmail.com | X19: 30 | Y19: 0 | Z19: 5 | AA19: 21100 | AB19: 0 | AC19: 0 | AD19: 0 | AE19: 0 | AF19: =SUM(AA19:AE19) -> 21100 | AG19: 0 | AH19: 0 | AI19: 0 | AJ19: 3600 | AL19: 0
